{"searchResult": {
   "errors": [   {
      "code": 200,
      "name": "DataProviderMessage",
      "severity": "INFORMATIONAL",
      "origin": "TOPS",
      "description": "F5293enhUnetV1 Error RETURN-CODE[6] EXPLANATION-CODE[997] RNP-RESP-CODE[3]"
   }],
   "searchOutput":    {
      "relatedServiceIndicator": "Y",
      "priorAuthorizationIndicator": "A",
      "radiologyAuthorizationIndicator": "A",
      "cardiologyAuthorizationIndicator": "A",
      "chemotherapyPriorAuthorizationIndicator": "A",
      "geneticTestingPriorAuthorizationIndicator": "A",
      "policyPlanParticipationIndicator": "",
      "claims":       [
                  {
            "filmOfficeNumber": "828",
            "filmLocatorNumber": "2018503637",
            "filmLocatorDate": "2020-07-03",
            "auditControlNumber": "AA18421604",
            "auditControlNumberSuffixCode": "01",
            "draftNumber": "0000023329",
            "headerCount": "0002",
            "firstServiceDate": "2020-06-11",
            "lastServiceDate": "2020-06-11",
            "processedDate": "2020-08-20",
            "processedTime": "04.41.13",
            "claimType": "PHYSICIAN",
            "providerTaxIdPrefix": "2",
            "providerTaxId": "421629846",
            "providerTaxIdSuffix": "00002",
            "providerName": "JONATHAN V WEITZMANN",
            "providerFirstName": "JONATHAN V",
            "providerLastName": "WEITZMANN",
            "totalCharged": "200.00",
            "totalDeductible": "0.00",
            "totalPaid": "0.00",
            "claimStatus": "CLOSED / LETTER SENT",
            "closedFlag": "Y",
            "paidFlag": "N",
            "pendedFlag": "N",
            "rejectedFlag": "N",
            "unprocessedFlag": "N",
            "adjudicateIndicator": "Manual",
            "remarkCode": "",
            "source": "TOPS",
            "paidStatus": "INN",
            "ppoIndicator": "I",
            "tier1ProcessIndicator": "N",
            "claimProtectedHealthIndicator": "",
            "authorizationNumber": "",
            "authorizationSourceId": "",
            "authorizationProcedureCode": "",
            "authorizationClaimLevelIndicator": "",
            "authorizationUniqueCount": "0",
            "primaryDiagnosis": "R52",
            "claimIndicator": "",
            "parsWaivIndicator": "",
            "parIndicator": "Y",
            "nonParIndicator": "",
            "deductibleFlag": "No",
            "memberId": "994061057",
            "memberIdPrefix": "S",
            "groupPolicy": "701648",
            "dependentNumber": "099",
            "firstName": "RAJIV",
            "lastName": "GANDHI",
            "relationshipCode": "EE",
            "system": "C",
            "planVariationCode": "0670",
            "reportingCode": "0670",
            "fundingResponsibility": "2",
            "patientPhiIndicator": "",
            "uhpIndicator": "",
            "providerTier": "I",
            "tpsmServiceCode": "99Z",
            "delegatedEncounterIndicator": "",
            "mskIndicator": "N",
            "totalPatientResponsibility": "0.00",
            "providerSpecialty": "NEP",
            "contractId": "167813308"
         },
                  {
            "filmOfficeNumber": "828",
            "filmLocatorNumber": "2018503637",
            "filmLocatorDate": "2020-07-03",
            "auditControlNumber": "AA18421604",
            "auditControlNumberSuffixCode": "01",
            "draftNumber": "0000023327",
            "headerCount": "0003",
            "firstServiceDate": "2020-06-11",
            "lastServiceDate": "2020-06-11",
            "processedDate": "2020-08-20",
            "processedTime": "04.40.07",
            "claimType": "PHYSICIAN",
            "providerTaxIdPrefix": "2",
            "providerTaxId": "421629846",
            "providerTaxIdSuffix": "00002",
            "providerName": "JONATHAN V WEITZMANN",
            "providerFirstName": "JONATHAN V",
            "providerLastName": "WEITZMANN",
            "totalCharged": "-200.00",
            "totalDeductible": "0.00",
            "totalPaid": "-53.11",
            "claimStatus": "PROCESSED",
            "closedFlag": "N",
            "paidFlag": "Y",
            "pendedFlag": "N",
            "rejectedFlag": "N",
            "unprocessedFlag": "N",
            "adjudicateIndicator": "Manual",
            "remarkCode": "ZU",
            "remarkDescription": "ACCOUNTING CORRECTIONS - ACCOUNTING DEFECTS - CLRC:",
            "source": "TOPS",
            "paidStatus": "INN",
            "ppoIndicator": "I",
            "tier1ProcessIndicator": "N",
            "claimProtectedHealthIndicator": "",
            "authorizationNumber": "",
            "authorizationSourceId": "",
            "authorizationProcedureCode": "",
            "authorizationClaimLevelIndicator": "",
            "authorizationUniqueCount": "0",
            "primaryDiagnosis": "R52",
            "claimIndicator": "",
            "parsWaivIndicator": "",
            "parIndicator": "",
            "nonParIndicator": "Y",
            "deductibleFlag": "No",
            "memberId": "994061057",
            "memberIdPrefix": "S",
            "groupPolicy": "701648",
            "dependentNumber": "099",
            "firstName": "RAJIV",
            "lastName": "GANDHI",
            "relationshipCode": "EE",
            "system": "C",
            "planVariationCode": "0670",
            "reportingCode": "0670",
            "fundingResponsibility": "2",
            "patientPhiIndicator": "",
            "uhpIndicator": "",
            "providerTier": "I",
            "tpsmServiceCode": "99Z",
            "delegatedEncounterIndicator": "",
            "mskIndicator": "N",
            "totalPatientResponsibility": "-50.00",
            "providerSpecialty": "NEP",
            "contractId": "167813308"
         },
                  {
            "filmOfficeNumber": "828",
            "filmLocatorNumber": "2018503637",
            "filmLocatorDate": "2020-07-03",
            "auditControlNumber": "AA18421604",
            "auditControlNumberSuffixCode": "01",
            "draftNumber": "0000023328",
            "headerCount": "0004",
            "firstServiceDate": "2020-06-11",
            "lastServiceDate": "2020-06-11",
            "processedDate": "2020-08-20",
            "processedTime": "04.39.50",
            "claimType": "PHYSICIAN",
            "providerTaxIdPrefix": "2",
            "providerTaxId": "421629846",
            "providerTaxIdSuffix": "00002",
            "providerName": "JONATHAN V WEITZMANN",
            "providerFirstName": "JONATHAN V",
            "providerLastName": "WEITZMANN",
            "totalCharged": "-0.37",
            "totalDeductible": "0.00",
            "totalPaid": "-0.37",
            "claimStatus": "PROCESSED",
            "closedFlag": "N",
            "paidFlag": "Y",
            "pendedFlag": "N",
            "rejectedFlag": "N",
            "unprocessedFlag": "N",
            "adjudicateIndicator": "Manual",
            "remarkCode": "ZU",
            "remarkDescription": "ACCOUNTING CORRECTIONS - ACCOUNTING DEFECTS - CLRC:",
            "source": "TOPS",
            "paidStatus": "INN",
            "ppoIndicator": "I",
            "tier1ProcessIndicator": "",
            "claimProtectedHealthIndicator": "",
            "authorizationNumber": "",
            "authorizationSourceId": "",
            "authorizationProcedureCode": "",
            "authorizationClaimLevelIndicator": "",
            "authorizationUniqueCount": "0",
            "primaryDiagnosis": "R52",
            "claimIndicator": "",
            "parsWaivIndicator": "",
            "parIndicator": "",
            "nonParIndicator": "Y",
            "deductibleFlag": "No",
            "memberId": "994061057",
            "memberIdPrefix": "S",
            "groupPolicy": "701648",
            "dependentNumber": "099",
            "firstName": "RAJIV",
            "lastName": "GANDHI",
            "relationshipCode": "EE",
            "system": "C",
            "planVariationCode": "0670",
            "reportingCode": "0670",
            "fundingResponsibility": "2",
            "patientPhiIndicator": "",
            "uhpIndicator": "",
            "providerTier": "O",
            "tpsmServiceCode": "99Z",
            "delegatedEncounterIndicator": "",
            "mskIndicator": "N",
            "totalPatientResponsibility": "0.00",
            "providerSpecialty": "NEP",
            "contractId": "000000000"
         },
                  {
            "filmOfficeNumber": "828",
            "filmLocatorNumber": "2018503637",
            "filmLocatorDate": "2020-07-03",
            "auditControlNumber": "AA18421604",
            "auditControlNumberSuffixCode": "01",
            "draftNumber": "0000023328",
            "headerCount": "0005",
            "firstServiceDate": "2020-06-11",
            "lastServiceDate": "2020-06-11",
            "processedDate": "2020-08-20",
            "processedTime": "04.39.20",
            "claimType": "PHYSICIAN",
            "providerTaxIdPrefix": "2",
            "providerTaxId": "421629846",
            "providerTaxIdSuffix": "00002",
            "providerName": "JONATHAN V WEITZMANN",
            "providerFirstName": "JONATHAN V",
            "providerLastName": "WEITZMANN",
            "totalCharged": "0.37",
            "totalDeductible": "0.00",
            "totalPaid": "0.37",
            "claimStatus": "PROCESSED",
            "closedFlag": "N",
            "paidFlag": "Y",
            "pendedFlag": "N",
            "rejectedFlag": "N",
            "unprocessedFlag": "N",
            "adjudicateIndicator": "Manual",
            "remarkCode": "81",
            "remarkDescription": "ACCOUNTING ADJUSTMENTS:",
            "source": "TOPS",
            "paidStatus": "INN",
            "ppoIndicator": "I",
            "tier1ProcessIndicator": "N",
            "claimProtectedHealthIndicator": "",
            "authorizationNumber": "",
            "authorizationSourceId": "",
            "authorizationProcedureCode": "",
            "authorizationClaimLevelIndicator": "",
            "authorizationUniqueCount": "0",
            "primaryDiagnosis": "R52",
            "claimIndicator": "",
            "parsWaivIndicator": "",
            "parIndicator": "",
            "nonParIndicator": "Y",
            "deductibleFlag": "No",
            "memberId": "994061057",
            "memberIdPrefix": "S",
            "groupPolicy": "701648",
            "dependentNumber": "099",
            "firstName": "RAJIV",
            "lastName": "GANDHI",
            "relationshipCode": "EE",
            "system": "C",
            "planVariationCode": "0670",
            "reportingCode": "0670",
            "fundingResponsibility": "2",
            "patientPhiIndicator": "",
            "uhpIndicator": "",
            "providerTier": "I",
            "tpsmServiceCode": "99Z",
            "delegatedEncounterIndicator": "",
            "mskIndicator": "N",
            "totalPatientResponsibility": "0.00",
            "providerSpecialty": "NEP",
            "contractId": "167813308"
         },
                  {
            "filmOfficeNumber": "828",
            "filmLocatorNumber": "2018503637",
            "filmLocatorDate": "2020-07-03",
            "auditControlNumber": "AA18421604",
            "auditControlNumberSuffixCode": "01",
            "draftNumber": "0000023327",
            "headerCount": "0005",
            "firstServiceDate": "2020-06-11",
            "lastServiceDate": "2020-06-11",
            "processedDate": "2020-08-20",
            "processedTime": "04.39.20",
            "claimType": "PHYSICIAN",
            "providerTaxIdPrefix": "2",
            "providerTaxId": "421629846",
            "providerTaxIdSuffix": "00002",
            "providerName": "JONATHAN V WEITZMANN",
            "providerFirstName": "JONATHAN V",
            "providerLastName": "WEITZMANN",
            "totalCharged": "200.00",
            "totalDeductible": "0.00",
            "totalPaid": "53.11",
            "claimStatus": "PROCESSED",
            "closedFlag": "N",
            "paidFlag": "Y",
            "pendedFlag": "N",
            "rejectedFlag": "N",
            "unprocessedFlag": "N",
            "adjudicateIndicator": "Manual",
            "remarkCode": "81",
            "remarkDescription": "ACCOUNTING ADJUSTMENTS:",
            "source": "TOPS",
            "paidStatus": "INN",
            "ppoIndicator": "I",
            "tier1ProcessIndicator": "N",
            "claimProtectedHealthIndicator": "",
            "authorizationNumber": "",
            "authorizationSourceId": "",
            "authorizationProcedureCode": "",
            "authorizationClaimLevelIndicator": "",
            "authorizationUniqueCount": "0",
            "primaryDiagnosis": "R52",
            "claimIndicator": "",
            "parsWaivIndicator": "",
            "parIndicator": "",
            "nonParIndicator": "Y",
            "deductibleFlag": "No",
            "memberId": "994061057",
            "memberIdPrefix": "S",
            "groupPolicy": "701648",
            "dependentNumber": "099",
            "firstName": "RAJIV",
            "lastName": "GANDHI",
            "relationshipCode": "EE",
            "system": "C",
            "planVariationCode": "0670",
            "reportingCode": "0670",
            "fundingResponsibility": "2",
            "patientPhiIndicator": "",
            "uhpIndicator": "",
            "providerTier": "I",
            "tpsmServiceCode": "99Z",
            "delegatedEncounterIndicator": "",
            "mskIndicator": "N",
            "totalPatientResponsibility": "50.00",
            "providerSpecialty": "NEP",
            "contractId": "167813308"
         },
                  {
            "filmOfficeNumber": "828",
            "filmLocatorNumber": "2018503637",
            "filmLocatorDate": "2020-07-03",
            "auditControlNumber": "AA18421604",
            "auditControlNumberSuffixCode": "01",
            "draftNumber": "0000023273",
            "headerCount": "0006",
            "firstServiceDate": "2020-06-29",
            "lastServiceDate": "2020-06-29",
            "processedDate": "2020-07-29",
            "processedTime": "04.58.42",
            "claimType": "HOSPITAL",
            "providerTaxIdPrefix": "2",
            "providerTaxId": "010858704",
            "providerTaxIdSuffix": "00001",
            "providerName": "FORT PIERCE ORTHOPAEDICS",
            "facilityName": "FORT PIERCE ORTHOPAEDICS",
            "totalCharged": "200.00",
            "totalDeductible": "0.00",
            "totalPaid": "31.32",
            "claimStatus": "PROCESSED",
            "closedFlag": "N",
            "paidFlag": "Y",
            "pendedFlag": "N",
            "rejectedFlag": "N",
            "unprocessedFlag": "N",
            "adjudicateIndicator": "Manual",
            "remarkCode": "",
            "source": "TOPS",
            "paidStatus": "INN",
            "ppoIndicator": "I",
            "tier1ProcessIndicator": "N",
            "claimProtectedHealthIndicator": "",
            "authorizationNumber": "",
            "authorizationSourceId": "",
            "authorizationProcedureCode": "",
            "authorizationClaimLevelIndicator": "",
            "authorizationUniqueCount": "0",
            "primaryDiagnosis": "R52",
            "claimIndicator": "",
            "parsWaivIndicator": "",
            "parIndicator": "",
            "nonParIndicator": "Y",
            "deductibleFlag": "No",
            "memberId": "994061057",
            "memberIdPrefix": "S",
            "groupPolicy": "701648",
            "dependentNumber": "099",
            "firstName": "RAJIV",
            "lastName": "GANDHI",
            "relationshipCode": "EE",
            "system": "C",
            "planVariationCode": "0670",
            "reportingCode": "0670",
            "fundingResponsibility": "2",
            "patientPhiIndicator": "",
            "uhpIndicator": "",
            "providerTier": "I",
            "tpsmServiceCode": "99Z",
            "delegatedEncounterIndicator": "",
            "mskIndicator": "N",
            "totalPatientResponsibility": "30.00",
            "providerSpecialty": "ORS",
            "contractId": "096048841"
         },
                  {
            "filmOfficeNumber": "828",
            "filmLocatorNumber": "2008603616",
            "filmLocatorDate": "2020-03-26",
            "auditControlNumber": "AA11791857",
            "auditControlNumberSuffixCode": "02",
            "draftNumber": "0000023220",
            "headerCount": "0007",
            "firstServiceDate": "2020-03-09",
            "lastServiceDate": "2020-03-09",
            "processedDate": "2020-04-23",
            "processedTime": "06.25.59",
            "claimType": "HOSPITAL",
            "providerTaxIdPrefix": "2",
            "providerTaxId": "240795682",
            "providerTaxIdSuffix": "00001",
            "providerName": "MOUNT NITTANY MEDICAL CENTER",
            "facilityName": "MOUNT NITTANY MEDICAL CENTER",
            "totalCharged": "628.00",
            "totalDeductible": "0.00",
            "totalPaid": "0.00",
            "claimStatus": "CLOSED / LETTER SENT",
            "closedFlag": "Y",
            "paidFlag": "N",
            "pendedFlag": "N",
            "rejectedFlag": "N",
            "unprocessedFlag": "N",
            "adjudicateIndicator": "Manual",
            "remarkCode": "",
            "source": "TOPS",
            "paidStatus": "INN",
            "ppoIndicator": "I",
            "tier1ProcessIndicator": "N",
            "claimProtectedHealthIndicator": "",
            "authorizationNumber": "",
            "authorizationSourceId": "",
            "authorizationProcedureCode": "",
            "authorizationClaimLevelIndicator": "",
            "authorizationUniqueCount": "0",
            "primaryDiagnosis": "K8010",
            "claimIndicator": "",
            "parsWaivIndicator": "",
            "parIndicator": "Y",
            "nonParIndicator": "",
            "deductibleFlag": "No",
            "memberId": "994061057",
            "memberIdPrefix": "S",
            "groupPolicy": "701648",
            "dependentNumber": "099",
            "firstName": "RAJIV",
            "lastName": "GANDHI",
            "relationshipCode": "EE",
            "system": "C",
            "planVariationCode": "0670",
            "reportingCode": "0670",
            "fundingResponsibility": "2",
            "patientPhiIndicator": "",
            "uhpIndicator": "",
            "providerTier": "I",
            "tpsmServiceCode": "99Z",
            "delegatedEncounterIndicator": "",
            "mskIndicator": "N",
            "totalPatientResponsibility": "0.00",
            "providerSpecialty": "",
            "contractId": "162094818"
         },
                  {
            "filmOfficeNumber": "828",
            "filmLocatorNumber": "2007703619",
            "filmLocatorDate": "2020-03-17",
            "auditControlNumber": "AA11720830",
            "auditControlNumberSuffixCode": "01",
            "draftNumber": "0000023034",
            "headerCount": "0014",
            "firstServiceDate": "2020-03-01",
            "lastServiceDate": "2020-03-01",
            "processedDate": "2020-03-31",
            "processedTime": "15.09.44",
            "claimType": "PHYSICIAN",
            "providerTaxIdPrefix": "2",
            "providerTaxId": "262388378",
            "providerTaxIdSuffix": "00012",
            "providerName": "ALIREZA FALAHATI-NINI",
            "providerFirstName": "ALIREZA",
            "providerLastName": "FALAHATI-NINI",
            "totalCharged": "167.00",
            "totalDeductible": "10.00",
            "totalPaid": "0.00",
            "claimStatus": "PROCESSED",
            "closedFlag": "N",
            "paidFlag": "Y",
            "pendedFlag": "N",
            "rejectedFlag": "N",
            "unprocessedFlag": "N",
            "adjudicateIndicator": "Auto",
            "remarkCode": "",
            "source": "TOPS",
            "paidStatus": "INN",
            "ppoIndicator": "I",
            "tier1ProcessIndicator": "N",
            "claimProtectedHealthIndicator": "",
            "authorizationNumber": "",
            "authorizationSourceId": "",
            "authorizationProcedureCode": "",
            "authorizationClaimLevelIndicator": "N",
            "authorizationUniqueCount": "0",
            "primaryDiagnosis": "J020",
            "claimIndicator": "",
            "parsWaivIndicator": "",
            "parIndicator": "Y",
            "nonParIndicator": "",
            "deductibleFlag": "Yes",
            "memberId": "994061057",
            "memberIdPrefix": "S",
            "groupPolicy": "701648",
            "dependentNumber": "099",
            "firstName": "RAJIV",
            "lastName": "GANDHI",
            "relationshipCode": "EE",
            "system": "C",
            "planVariationCode": "0670",
            "reportingCode": "0670",
            "fundingResponsibility": "2",
            "patientPhiIndicator": "",
            "uhpIndicator": "",
            "providerTier": "I",
            "tpsmServiceCode": "99Z",
            "delegatedEncounterIndicator": "",
            "mskIndicator": "N",
            "totalPatientResponsibility": "10.00",
            "providerSpecialty": "END",
            "contractId": "033282356"
         },
                  {
            "filmOfficeNumber": "828",
            "filmLocatorNumber": "2007603622",
            "filmLocatorDate": "2020-03-16",
            "auditControlNumber": "AA11639456",
            "auditControlNumberSuffixCode": "01",
            "draftNumber": "0000023160",
            "headerCount": "0008",
            "firstServiceDate": "2020-02-14",
            "lastServiceDate": "2020-02-14",
            "processedDate": "2020-04-14",
            "processedTime": "00.10.48",
            "claimType": "HOSPITAL",
            "providerTaxIdPrefix": "2",
            "providerTaxId": "811108738",
            "providerTaxIdSuffix": "00004",
            "providerName": "MATHEW DEVILLE CHIROPRACTIC",
            "facilityName": "MATHEW DEVILLE CHIROPRACTIC",
            "totalCharged": "850.00",
            "totalDeductible": "0.00",
            "totalPaid": "631.41",
            "claimStatus": "PROCESSED",
            "closedFlag": "N",
            "paidFlag": "Y",
            "pendedFlag": "N",
            "rejectedFlag": "N",
            "unprocessedFlag": "N",
            "adjudicateIndicator": "Auto",
            "remarkCode": "",
            "source": "TOPS",
            "paidStatus": "OON",
            "ppoIndicator": "O",
            "tier1ProcessIndicator": "N",
            "claimProtectedHealthIndicator": "",
            "authorizationNumber": "",
            "authorizationSourceId": "",
            "authorizationProcedureCode": "",
            "authorizationClaimLevelIndicator": "",
            "authorizationUniqueCount": "0",
            "primaryDiagnosis": "M546",
            "claimIndicator": "",
            "parsWaivIndicator": "",
            "parIndicator": "",
            "nonParIndicator": "Y",
            "deductibleFlag": "No",
            "memberId": "994061057",
            "memberIdPrefix": "S",
            "groupPolicy": "701648",
            "dependentNumber": "099",
            "firstName": "RAJIV",
            "lastName": "GANDHI",
            "relationshipCode": "EE",
            "system": "C",
            "planVariationCode": "0670",
            "reportingCode": "0670",
            "fundingResponsibility": "2",
            "patientPhiIndicator": "",
            "uhpIndicator": "",
            "providerTier": "O",
            "tpsmServiceCode": "99Z",
            "delegatedEncounterIndicator": "",
            "mskIndicator": "N",
            "totalPatientResponsibility": "218.59",
            "providerSpecialty": "CM",
            "contractId": "000000000"
         },
                  {
            "filmOfficeNumber": "828",
            "filmLocatorNumber": "2007503605",
            "filmLocatorDate": "2020-03-15",
            "auditControlNumber": "AA11639414",
            "auditControlNumberSuffixCode": "02",
            "draftNumber": "0000022974",
            "headerCount": "0016",
            "firstServiceDate": "2019-12-21",
            "lastServiceDate": "2019-12-24",
            "processedDate": "2020-03-29",
            "processedTime": "04.14.15",
            "claimType": "HOSPITAL",
            "providerTaxIdPrefix": "2",
            "providerTaxId": "430653493",
            "providerTaxIdSuffix": "00044",
            "providerName": "MERCY HOSPITAL ST LOUIS",
            "facilityName": "MERCY HOSPITAL ST LOUIS",
            "totalCharged": "1447.68",
            "totalDeductible": "0.00",
            "totalPaid": "881.00",
            "claimStatus": "PROCESSED",
            "closedFlag": "N",
            "paidFlag": "Y",
            "pendedFlag": "N",
            "rejectedFlag": "N",
            "unprocessedFlag": "N",
            "adjudicateIndicator": "Auto",
            "remarkCode": "",
            "source": "TOPS",
            "paidStatus": "INN",
            "ppoIndicator": "I",
            "tier1ProcessIndicator": "N",
            "claimProtectedHealthIndicator": "",
            "authorizationNumber": "",
            "authorizationSourceId": "",
            "authorizationProcedureCode": "",
            "authorizationClaimLevelIndicator": "N",
            "authorizationUniqueCount": "0",
            "primaryDiagnosis": "S82002A",
            "claimIndicator": "",
            "parsWaivIndicator": "",
            "parIndicator": "Y",
            "nonParIndicator": "",
            "deductibleFlag": "No",
            "memberId": "994061057",
            "memberIdPrefix": "S",
            "groupPolicy": "701648",
            "dependentNumber": "099",
            "firstName": "RAJIV",
            "lastName": "GANDHI",
            "relationshipCode": "EE",
            "system": "C",
            "planVariationCode": "0670",
            "reportingCode": "0670",
            "fundingResponsibility": "2",
            "patientPhiIndicator": "",
            "uhpIndicator": "",
            "providerTier": "I",
            "tpsmServiceCode": "99Z",
            "delegatedEncounterIndicator": "",
            "mskIndicator": "N",
            "totalPatientResponsibility": "0.00",
            "providerSpecialty": "",
            "contractId": "170009846"
         },
                  {
            "filmOfficeNumber": "828",
            "filmLocatorNumber": "2007503603",
            "filmLocatorDate": "2020-03-15",
            "auditControlNumber": "AA11639418",
            "auditControlNumberSuffixCode": "02",
            "draftNumber": "0000023031",
            "headerCount": "0015",
            "firstServiceDate": "2020-02-07",
            "lastServiceDate": "2020-02-07",
            "processedDate": "2020-03-31",
            "processedTime": "11.09.52",
            "claimType": "HOSPITAL",
            "providerTaxIdPrefix": "2",
            "providerTaxId": "590725553",
            "providerTaxIdSuffix": "00044",
            "providerName": "ADVENTHEALTH SEBRING",
            "facilityName": "ADVENTHEALTH SEBRING",
            "totalCharged": "1823.00",
            "totalDeductible": "0.00",
            "totalPaid": "0.00",
            "claimStatus": "CLOSED / LETTER SENT",
            "closedFlag": "Y",
            "paidFlag": "N",
            "pendedFlag": "N",
            "rejectedFlag": "N",
            "unprocessedFlag": "N",
            "adjudicateIndicator": "Manual",
            "remarkCode": "",
            "source": "TOPS",
            "paidStatus": "INN",
            "ppoIndicator": "I",
            "tier1ProcessIndicator": "N",
            "claimProtectedHealthIndicator": "",
            "authorizationNumber": "",
            "authorizationSourceId": "",
            "authorizationProcedureCode": "",
            "authorizationClaimLevelIndicator": "",
            "authorizationUniqueCount": "0",
            "primaryDiagnosis": "H33022",
            "claimIndicator": "",
            "parsWaivIndicator": "",
            "parIndicator": "Y",
            "nonParIndicator": "",
            "deductibleFlag": "No",
            "memberId": "994061057",
            "memberIdPrefix": "S",
            "groupPolicy": "701648",
            "dependentNumber": "099",
            "firstName": "RAJIV",
            "lastName": "GANDHI",
            "relationshipCode": "EE",
            "system": "C",
            "planVariationCode": "0670",
            "reportingCode": "0670",
            "fundingResponsibility": "2",
            "patientPhiIndicator": "",
            "uhpIndicator": "",
            "providerTier": "I",
            "tpsmServiceCode": "220",
            "delegatedEncounterIndicator": "",
            "mskIndicator": "N",
            "totalPatientResponsibility": "0.00",
            "providerSpecialty": "",
            "contractId": "168940492"
         },
                  {
            "filmOfficeNumber": "828",
            "filmLocatorNumber": "2007203601",
            "filmLocatorDate": "2020-03-12",
            "auditControlNumber": "AA11625111",
            "auditControlNumberSuffixCode": "01",
            "draftNumber": "0000022969",
            "headerCount": "0017",
            "firstServiceDate": "2020-02-24",
            "lastServiceDate": "2020-02-24",
            "processedDate": "2020-03-27",
            "processedTime": "05.30.55",
            "claimType": "PHYSICIAN",
            "providerTaxIdPrefix": "2",
            "providerTaxId": "262388378",
            "providerTaxIdSuffix": "00012",
            "providerName": "ALIREZA FALAHATI-NINI",
            "providerFirstName": "ALIREZA",
            "providerLastName": "FALAHATI-NINI",
            "totalCharged": "167.00",
            "totalDeductible": "10.00",
            "totalPaid": "95.60",
            "claimStatus": "PROCESSED",
            "closedFlag": "N",
            "paidFlag": "Y",
            "pendedFlag": "N",
            "rejectedFlag": "N",
            "unprocessedFlag": "N",
            "adjudicateIndicator": "Manual",
            "remarkCode": "",
            "source": "TOPS",
            "paidStatus": "INN",
            "ppoIndicator": "I",
            "tier1ProcessIndicator": "N",
            "claimProtectedHealthIndicator": "",
            "authorizationNumber": "",
            "authorizationSourceId": "",
            "authorizationProcedureCode": "",
            "authorizationClaimLevelIndicator": "N",
            "authorizationUniqueCount": "0",
            "primaryDiagnosis": "J020",
            "claimIndicator": "",
            "parsWaivIndicator": "",
            "parIndicator": "",
            "nonParIndicator": "Y",
            "deductibleFlag": "Yes",
            "memberId": "994061057",
            "memberIdPrefix": "S",
            "groupPolicy": "701648",
            "dependentNumber": "099",
            "firstName": "RAJIV",
            "lastName": "GANDHI",
            "relationshipCode": "EE",
            "system": "C",
            "planVariationCode": "0670",
            "reportingCode": "0670",
            "fundingResponsibility": "2",
            "patientPhiIndicator": "",
            "uhpIndicator": "",
            "providerTier": "I",
            "tpsmServiceCode": "99Z",
            "delegatedEncounterIndicator": "",
            "mskIndicator": "N",
            "totalPatientResponsibility": "60.00",
            "providerSpecialty": "END",
            "contractId": "033282356"
         },
                  {
            "filmOfficeNumber": "828",
            "filmLocatorNumber": "2005103644",
            "filmLocatorDate": "2020-02-20",
            "auditControlNumber": "AA09852444",
            "auditControlNumberSuffixCode": "01",
            "draftNumber": "0000023157",
            "headerCount": "0010",
            "firstServiceDate": "2020-01-21",
            "lastServiceDate": "2020-01-21",
            "processedDate": "2020-04-14",
            "processedTime": "00.10.33",
            "claimType": "HOSPITAL",
            "providerTaxIdPrefix": "8",
            "providerTaxId": "362169147",
            "providerTaxIdSuffix": "00279",
            "providerName": "ADVOCATE GOOD SHEPHERD HEALTH",
            "facilityName": "ADVOCATE GOOD SHEPHERD HEALTH",
            "totalCharged": "1093.00",
            "totalDeductible": "0.00",
            "totalPaid": "183.15",
            "claimStatus": "PROCESSED",
            "closedFlag": "N",
            "paidFlag": "Y",
            "pendedFlag": "N",
            "rejectedFlag": "N",
            "unprocessedFlag": "N",
            "adjudicateIndicator": "Auto",
            "remarkCode": "",
            "source": "TOPS",
            "paidStatus": "OON",
            "ppoIndicator": "O",
            "tier1ProcessIndicator": "N",
            "claimProtectedHealthIndicator": "",
            "authorizationNumber": "",
            "authorizationSourceId": "",
            "authorizationProcedureCode": "",
            "authorizationClaimLevelIndicator": "",
            "authorizationUniqueCount": "0",
            "primaryDiagnosis": "G802",
            "claimIndicator": "",
            "parsWaivIndicator": "",
            "parIndicator": "",
            "nonParIndicator": "Y",
            "deductibleFlag": "No",
            "memberId": "994061057",
            "memberIdPrefix": "S",
            "groupPolicy": "701648",
            "dependentNumber": "099",
            "firstName": "RAJIV",
            "lastName": "GANDHI",
            "relationshipCode": "EE",
            "system": "C",
            "planVariationCode": "0670",
            "reportingCode": "0670",
            "fundingResponsibility": "2",
            "patientPhiIndicator": "",
            "uhpIndicator": "",
            "providerTier": "O",
            "tpsmServiceCode": "316",
            "delegatedEncounterIndicator": "",
            "mskIndicator": "N",
            "totalPatientResponsibility": "909.85",
            "providerSpecialty": "ACU",
            "contractId": "000000000"
         },
                  {
            "filmOfficeNumber": "828",
            "filmLocatorNumber": "2005103642",
            "filmLocatorDate": "2020-02-20",
            "auditControlNumber": "AA09852495",
            "auditControlNumberSuffixCode": "01",
            "draftNumber": "0000023158",
            "headerCount": "0009",
            "firstServiceDate": "2020-01-26",
            "lastServiceDate": "2020-01-26",
            "processedDate": "2020-04-14",
            "processedTime": "00.10.35",
            "claimType": "HOSPITAL",
            "providerTaxIdPrefix": "2",
            "providerTaxId": "811108738",
            "providerTaxIdSuffix": "00004",
            "providerName": "MATHEW DEVILLE CHIROPRACTIC",
            "facilityName": "MATHEW DEVILLE CHIROPRACTIC",
            "totalCharged": "850.00",
            "totalDeductible": "0.00",
            "totalPaid": "595.00",
            "claimStatus": "PROCESSED",
            "closedFlag": "N",
            "paidFlag": "Y",
            "pendedFlag": "N",
            "rejectedFlag": "N",
            "unprocessedFlag": "N",
            "adjudicateIndicator": "Auto",
            "remarkCode": "",
            "source": "TOPS",
            "paidStatus": "OON",
            "ppoIndicator": "O",
            "tier1ProcessIndicator": "N",
            "claimProtectedHealthIndicator": "",
            "authorizationNumber": "",
            "authorizationSourceId": "",
            "authorizationProcedureCode": "",
            "authorizationClaimLevelIndicator": "",
            "authorizationUniqueCount": "0",
            "primaryDiagnosis": "M546",
            "claimIndicator": "",
            "parsWaivIndicator": "",
            "parIndicator": "",
            "nonParIndicator": "Y",
            "deductibleFlag": "No",
            "memberId": "994061057",
            "memberIdPrefix": "S",
            "groupPolicy": "701648",
            "dependentNumber": "099",
            "firstName": "RAJIV",
            "lastName": "GANDHI",
            "relationshipCode": "EE",
            "system": "C",
            "planVariationCode": "0670",
            "reportingCode": "0670",
            "fundingResponsibility": "2",
            "patientPhiIndicator": "",
            "uhpIndicator": "",
            "providerTier": "O",
            "tpsmServiceCode": "99Z",
            "delegatedEncounterIndicator": "",
            "mskIndicator": "N",
            "totalPatientResponsibility": "255.00",
            "providerSpecialty": "CM",
            "contractId": "000000000"
         },
                  {
            "filmOfficeNumber": "828",
            "filmLocatorNumber": "2005103634",
            "filmLocatorDate": "2020-02-20",
            "auditControlNumber": "AA09804757",
            "auditControlNumberSuffixCode": "01",
            "draftNumber": "0000023155",
            "headerCount": "0011",
            "firstServiceDate": "2020-01-16",
            "lastServiceDate": "2020-01-16",
            "processedDate": "2020-04-14",
            "processedTime": "00.10.29",
            "claimType": "HOSPITAL",
            "providerTaxIdPrefix": "2",
            "providerTaxId": "220820545",
            "providerTaxIdSuffix": "00015",
            "providerName": "CHRIST HOSPITAL",
            "facilityName": "CHRIST HOSPITAL",
            "totalCharged": "16143.00",
            "totalDeductible": "0.00",
            "totalPaid": "0.00",
            "claimStatus": "PROCESSED",
            "closedFlag": "N",
            "paidFlag": "Y",
            "pendedFlag": "N",
            "rejectedFlag": "N",
            "unprocessedFlag": "N",
            "adjudicateIndicator": "Auto",
            "remarkCode": "",
            "source": "TOPS",
            "paidStatus": "OON",
            "ppoIndicator": "O",
            "tier1ProcessIndicator": "N",
            "claimProtectedHealthIndicator": "",
            "authorizationNumber": "",
            "authorizationSourceId": "",
            "authorizationProcedureCode": "",
            "authorizationClaimLevelIndicator": "",
            "authorizationUniqueCount": "0",
            "primaryDiagnosis": "H33022",
            "claimIndicator": "",
            "parsWaivIndicator": "",
            "parIndicator": "",
            "nonParIndicator": "Y",
            "deductibleFlag": "No",
            "memberId": "994061057",
            "memberIdPrefix": "S",
            "groupPolicy": "701648",
            "dependentNumber": "099",
            "firstName": "RAJIV",
            "lastName": "GANDHI",
            "relationshipCode": "EE",
            "system": "C",
            "planVariationCode": "0670",
            "reportingCode": "0670",
            "fundingResponsibility": "2",
            "patientPhiIndicator": "",
            "uhpIndicator": "",
            "providerTier": "O",
            "tpsmServiceCode": "99Z",
            "delegatedEncounterIndicator": "",
            "mskIndicator": "N",
            "totalPatientResponsibility": "0.00",
            "providerSpecialty": "",
            "contractId": "000000000"
         },
                  {
            "filmOfficeNumber": "828",
            "filmLocatorNumber": "2005103630",
            "filmLocatorDate": "2020-02-20",
            "auditControlNumber": "AA09804835",
            "auditControlNumberSuffixCode": "01",
            "draftNumber": "0000023427",
            "headerCount": "0001",
            "firstServiceDate": "2020-01-21",
            "lastServiceDate": "2020-01-21",
            "processedDate": "2020-08-28",
            "processedTime": "12.47.34",
            "claimType": "HOSPITAL",
            "providerTaxIdPrefix": "2",
            "providerTaxId": "010858704",
            "providerTaxIdSuffix": "00001",
            "providerName": "FORT PIERCE ORTHOPAEDICS",
            "facilityName": "FORT PIERCE ORTHOPAEDICS",
            "totalCharged": "850.00",
            "totalDeductible": "230.00",
            "totalPaid": "620.00",
            "claimStatus": "PROCESSED",
            "closedFlag": "N",
            "paidFlag": "Y",
            "pendedFlag": "N",
            "rejectedFlag": "N",
            "unprocessedFlag": "N",
            "adjudicateIndicator": "Manual",
            "remarkCode": "",
            "source": "TOPS",
            "paidStatus": "INN",
            "ppoIndicator": "I",
            "tier1ProcessIndicator": "",
            "claimProtectedHealthIndicator": "",
            "authorizationNumber": "",
            "authorizationSourceId": "",
            "authorizationProcedureCode": "",
            "authorizationClaimLevelIndicator": "",
            "authorizationUniqueCount": "0",
            "primaryDiagnosis": "M546",
            "claimIndicator": "",
            "parsWaivIndicator": "",
            "parIndicator": "",
            "nonParIndicator": "Y",
            "deductibleFlag": "Yes",
            "memberId": "994061057",
            "memberIdPrefix": "S",
            "groupPolicy": "701648",
            "dependentNumber": "099",
            "firstName": "RAJIV",
            "lastName": "GANDHI",
            "relationshipCode": "EE",
            "system": "C",
            "planVariationCode": "0670",
            "reportingCode": "0670",
            "fundingResponsibility": "2",
            "patientPhiIndicator": "",
            "uhpIndicator": "",
            "providerTier": "O",
            "tpsmServiceCode": "99Z",
            "delegatedEncounterIndicator": "",
            "mskIndicator": "N",
            "totalPatientResponsibility": "230.00",
            "providerSpecialty": "ORS",
            "contractId": "000000000"
         },
                  {
            "filmOfficeNumber": "828",
            "filmLocatorNumber": "2005003629",
            "filmLocatorDate": "2020-02-19",
            "auditControlNumber": "AA09796563",
            "auditControlNumberSuffixCode": "01",
            "draftNumber": "0000023152",
            "headerCount": "0013",
            "firstServiceDate": "2020-01-22",
            "lastServiceDate": "2020-01-22",
            "processedDate": "2020-04-14",
            "processedTime": "00.08.25",
            "claimType": "HOSPITAL",
            "providerTaxIdPrefix": "2",
            "providerTaxId": "811108738",
            "providerTaxIdSuffix": "00004",
            "providerName": "MATHEW DEVILLE CHIROPRACTIC",
            "facilityName": "MATHEW DEVILLE CHIROPRACTIC",
            "totalCharged": "850.00",
            "totalDeductible": "500.00",
            "totalPaid": "245.00",
            "claimStatus": "PROCESSED",
            "closedFlag": "N",
            "paidFlag": "Y",
            "pendedFlag": "N",
            "rejectedFlag": "N",
            "unprocessedFlag": "N",
            "adjudicateIndicator": "Auto",
            "remarkCode": "",
            "source": "TOPS",
            "paidStatus": "OON",
            "ppoIndicator": "O",
            "tier1ProcessIndicator": "N",
            "claimProtectedHealthIndicator": "",
            "authorizationNumber": "",
            "authorizationSourceId": "",
            "authorizationProcedureCode": "",
            "authorizationClaimLevelIndicator": "",
            "authorizationUniqueCount": "0",
            "primaryDiagnosis": "M546",
            "claimIndicator": "",
            "parsWaivIndicator": "",
            "parIndicator": "",
            "nonParIndicator": "Y",
            "deductibleFlag": "Yes",
            "memberId": "994061057",
            "memberIdPrefix": "S",
            "groupPolicy": "701648",
            "dependentNumber": "099",
            "firstName": "RAJIV",
            "lastName": "GANDHI",
            "relationshipCode": "EE",
            "system": "C",
            "planVariationCode": "0670",
            "reportingCode": "0670",
            "fundingResponsibility": "2",
            "patientPhiIndicator": "",
            "uhpIndicator": "",
            "providerTier": "O",
            "tpsmServiceCode": "99Z",
            "delegatedEncounterIndicator": "",
            "mskIndicator": "N",
            "totalPatientResponsibility": "605.00",
            "providerSpecialty": "CM",
            "contractId": "000000000"
         },
                  {
            "filmOfficeNumber": "828",
            "filmLocatorNumber": "2002103601",
            "filmLocatorDate": "2020-01-21",
            "auditControlNumber": "AA09804756",
            "auditControlNumberSuffixCode": "01",
            "draftNumber": "0000023154",
            "headerCount": "0012",
            "firstServiceDate": "2020-01-16",
            "lastServiceDate": "2020-01-16",
            "processedDate": "2020-04-14",
            "processedTime": "00.09.33",
            "claimType": "HOSPITAL",
            "providerTaxIdPrefix": "2",
            "providerTaxId": "220820545",
            "providerTaxIdSuffix": "00015",
            "providerName": "CHRIST HOSPITAL",
            "facilityName": "CHRIST HOSPITAL",
            "totalCharged": "16143.00",
            "totalDeductible": "0.00",
            "totalPaid": "11300.10",
            "claimStatus": "PROCESSED",
            "closedFlag": "N",
            "paidFlag": "Y",
            "pendedFlag": "N",
            "rejectedFlag": "N",
            "unprocessedFlag": "N",
            "adjudicateIndicator": "Auto",
            "remarkCode": "",
            "source": "TOPS",
            "paidStatus": "OON",
            "ppoIndicator": "O",
            "tier1ProcessIndicator": "N",
            "claimProtectedHealthIndicator": "",
            "authorizationNumber": "",
            "authorizationSourceId": "",
            "authorizationProcedureCode": "",
            "authorizationClaimLevelIndicator": "",
            "authorizationUniqueCount": "0",
            "primaryDiagnosis": "H33022",
            "claimIndicator": "",
            "parsWaivIndicator": "",
            "parIndicator": "",
            "nonParIndicator": "Y",
            "deductibleFlag": "No",
            "memberId": "994061057",
            "memberIdPrefix": "S",
            "groupPolicy": "701648",
            "dependentNumber": "099",
            "firstName": "RAJIV",
            "lastName": "GANDHI",
            "relationshipCode": "EE",
            "system": "C",
            "planVariationCode": "0670",
            "reportingCode": "0670",
            "fundingResponsibility": "2",
            "patientPhiIndicator": "",
            "uhpIndicator": "",
            "providerTier": "O",
            "tpsmServiceCode": "99Z",
            "delegatedEncounterIndicator": "",
            "mskIndicator": "N",
            "totalPatientResponsibility": "0.00",
            "providerSpecialty": "",
            "contractId": "000000000"
         }
      ],
      "searchOutputMeta": {"pagingState":       {
         "moreData": false,
         "nextKey": ""
      }}
   }
}}