{
    "memberPolicies": [
        {
            "patientInfo": [
                {
                    "addressLine1": "1222 VALIANT DRIVE",
                    "addressLine2": "",
                    "city": "FLORIFISSANT",
                    "dateOfBirth": "1945-03-25",
                    "firstName": "ERIC",
                    "gender": "M",
                    "lastName": "GONDORIAN",
                    "middleName": "A",
                    "relationship": "subscriber",
                    "searched": "true",
                    "state": "MO",
                    "zip": "63031",
                    "patientKey": "TrAN1%2FCGn7j7h1mDCCbW7NWvvWNdGEYS75UgKBDX7wFMMfGxWkNHOJGykgnaQi8Zf1FOrtEBIcgb1EnFQ2a%2Fl4IB5PrfqczUPaFgAy4gLqmqB0p%2B9I4vRPDGwGinInO5InphnmzfoTIFbcuO%2BGX5gfTmeliYe1A7mK5RjO0ghHZ2sTy6EXI7lIn61KZxNxZ0%2Fm6AXL1FI6impouYSuTxuC%2F8HjDNaM8p%2Fm9yQsxDg%2F6XyDXV4iAXWDPTB5O1WJJNbmMCvf47Kts4UsjE99EmO3j%2FqA3ez3fV2Z0BL1zHkkH5D5MykSxU7rk9Ipz8LXgenfA0UnJPtUehWAI8ZCjkbp1JZc32KMC4QQBQPjC2iM6lWtLQQ2Bc4hNibpEsCsrea5aZhbbdXdMFz%2BqzSc8cxduBZ%2Beak4NavOKhLCyn5HJKqfruRQbpskLBX1njo%2B2QNv%2BY3%2BaOUe5EAqDsOyXuE4uY8qtbCyG%2BJO9MLHX3quxUUBE0tDoO%2FkRM2ZedaIMl6QfHoFFNeYT2Qa2vC9BRwWkMOhSlb%2Bm4%2BN8uFspa3GxgN7zHznwKkmi3%2B5%2B8Aky589iPlebewYDYGet2LkEWLahqVApqy60tK1MKRGjEI2zhcQ%2F1New2YHeyKN0jTpRWUy67g1KbYcrGUdL2L%2BUcPozoopHSScb46TTCC8J6MQ0xep%2FNbG6oG%2BG9AEpZ%2BVHXzupOlqIr%2BdXBC2cxfXvvM47Bx8Vok8I6CT9i1aFCpLlTPlsaPCi5dzQSK5wTFw5TAJokl4l1g7eSJXwgX6tvhxwADI7QNQJ3IRRoAUD5nMOQAWAZ%2FAkHZzJ%2FOrWmv2Zi5koZSKeJVAAncdRPvhTB%2F1vebOuNqg3R6f66kqdA%2By2L0eVGuQI8eLd4XFphypouOiU%3D",
                    "subscriberBoolean": true
                }
            ],
            "additionalCoverageInfo": [
              {
                  "additionalCoverage": "Yes",
                  "payerName": "MEDICARE PART A & B",
                  "memberId": "",
                  "phone": "",
                  "url": "",
                  "insuranceType": "Unable to determine",
                  "payerStatus": "Primary",
                  "coverageType": ""
               },
                    {
                  "additionalCoverage": "Yes",
                  "payerName": "UNITED HEALTHCARE COMPANIES MEDICARE ADVANTAGE",
                  "memberId": "",
                  "phone": "",
                  "url": "",
                  "insuranceType": "Unable to determine",
                  "payerStatus": "Primary",
                  "coverageType": ""
               }
            ],
            "deductibleInfo": {
                "found": false,
                "nonMainPlan": false,
                "inAndOutOfNetworkOnly": true,
                "message": "Member's plan does not have a deductible",
                "individual": {
                    "found": false,
                    "inNetwork": {
                        "found": false,
                        "customerNetworkTier1": false,
                        "planAmount": "",
                        "planAmountFrequency": "",
                        "remainingAmount": "",
                        "metYtdAmount": ""
                    },
                    "outOfNetwork": {
                        "found": false,
                        "customerNetworkTier1": false,
                        "planAmount": "",
                        "planAmountFrequency": "",
                        "remainingAmount": "",
                        "metYtdAmount": ""
                    },
                    "inNetworkTier1": {
                        "found": false,
                        "customerNetworkTier1": false,
                        "planAmount": "",
                        "planAmountFrequency": "",
                        "remainingAmount": "",
                        "metYtdAmount": ""
                    }
                },
                "family": {
                    "found": false,
                    "inNetwork": {
                        "found": false,
                        "customerNetworkTier1": false,
                        "planAmount": "",
                        "planAmountFrequency": "",
                        "remainingAmount": "",
                        "metYtdAmount": ""
                    },
                    "outOfNetwork": {
                        "found": false,
                        "customerNetworkTier1": false,
                        "planAmount": "",
                        "planAmountFrequency": "",
                        "remainingAmount": "",
                        "metYtdAmount": ""
                    },
                    "inNetworkTier1": {
                        "found": false,
                        "customerNetworkTier1": false,
                        "planAmount": "",
                        "planAmountFrequency": "",
                        "remainingAmount": "",
                        "metYtdAmount": ""
                    }
                }
            },
            "outOfPocketInfo": {
                "found": true,
                "nonMainPlan": false,
                "inAndOutOfNetworkOnly": false,
                "message": "",
                "individual": {
                    "found": true,
                    "inNetwork": {
                        "found": true,
                        "customerNetworkTier1": false,
                        "planAmount": "2900.0",
                        "planAmountFrequency": " (Service Year)",
                        "remainingAmount": "1870.36",
                        "metYtdAmount": "1029.64"
                    },
                    "outOfNetwork": {
                        "found": false,
                        "customerNetworkTier1": false,
                        "planAmount": "",
                        "planAmountFrequency": "",
                        "remainingAmount": "",
                        "metYtdAmount": ""
                    },
                    "inNetworkTier1": {
                        "found": false,
                        "customerNetworkTier1": false,
                        "planAmount": "",
                        "planAmountFrequency": "",
                        "remainingAmount": "",
                        "metYtdAmount": ""
                    }
                },
                "family": {
                    "found": true,
                    "inNetwork": {
                        "found": true,
                        "customerNetworkTier1": false,
                        "planAmount": "99999.99",
                        "planAmountFrequency": " (Service Year)",
                        "remainingAmount": "98970.35",
                        "metYtdAmount": "1029.64"
                    },
                    "outOfNetwork": {
                        "found": false,
                        "customerNetworkTier1": false,
                        "planAmount": "",
                        "planAmountFrequency": "",
                        "remainingAmount": "",
                        "metYtdAmount": ""
                    },
                    "inNetworkTier1": {
                        "found": false,
                        "customerNetworkTier1": false,
                        "planAmount": "",
                        "planAmountFrequency": "",
                        "remainingAmount": "",
                        "metYtdAmount": ""
                    }
                }
            },
            "copayMaxInfo": {
                "found": false,
                "nonMainPlan": false,
                "inAndOutOfNetworkOnly": false,
                "message": "Member's plan does not have a copay maximum",
                "individual": {
                    "found": false,
                    "inNetwork": {
                        "found": false,
                        "customerNetworkTier1": false,
                        "planAmount": "",
                        "planAmountFrequency": "",
                        "remainingAmount": "",
                        "metYtdAmount": ""
                    },
                    "outOfNetwork": {
                        "found": false,
                        "customerNetworkTier1": false,
                        "planAmount": "",
                        "planAmountFrequency": "",
                        "remainingAmount": "",
                        "metYtdAmount": ""
                    },
                    "inNetworkTier1": {
                        "found": false,
                        "customerNetworkTier1": false,
                        "planAmount": "",
                        "planAmountFrequency": "",
                        "remainingAmount": "",
                        "metYtdAmount": ""
                    }
                },
                "family": {
                    "found": false,
                    "inNetwork": {
                        "found": false,
                        "customerNetworkTier1": false,
                        "planAmount": "",
                        "planAmountFrequency": "",
                        "remainingAmount": "",
                        "metYtdAmount": ""
                    },
                    "outOfNetwork": {
                        "found": false,
                        "customerNetworkTier1": false,
                        "planAmount": "",
                        "planAmountFrequency": "",
                        "remainingAmount": "",
                        "metYtdAmount": ""
                    },
                    "inNetworkTier1": {
                        "found": false,
                        "customerNetworkTier1": false,
                        "planAmount": "",
                        "planAmountFrequency": "",
                        "remainingAmount": "",
                        "metYtdAmount": ""
                    }
                }
            },
            "outOfPocketMaxInfo": {
                "found": false,
                "nonMainPlan": false,
                "inAndOutOfNetworkOnly": false,
                "message": "Member's plan does not have an out of pocket 2 maximum",
                "individual": {
                    "found": false,
                    "inNetwork": {
                        "found": false,
                        "customerNetworkTier1": false,
                        "planAmount": "",
                        "planAmountFrequency": "",
                        "remainingAmount": "",
                        "metYtdAmount": ""
                    },
                    "outOfNetwork": {
                        "found": false,
                        "customerNetworkTier1": false,
                        "planAmount": "",
                        "planAmountFrequency": "",
                        "remainingAmount": "",
                        "metYtdAmount": ""
                    },
                    "inNetworkTier1": {
                        "found": false,
                        "customerNetworkTier1": false,
                        "planAmount": "",
                        "planAmountFrequency": "",
                        "remainingAmount": "",
                        "metYtdAmount": ""
                    }
                },
                "family": {
                    "found": false,
                    "inNetwork": {
                        "found": false,
                        "customerNetworkTier1": false,
                        "planAmount": "",
                        "planAmountFrequency": "",
                        "remainingAmount": "",
                        "metYtdAmount": ""
                    },
                    "outOfNetwork": {
                        "found": false,
                        "customerNetworkTier1": false,
                        "planAmount": "",
                        "planAmountFrequency": "",
                        "remainingAmount": "",
                        "metYtdAmount": ""
                    },
                    "inNetworkTier1": {
                        "found": false,
                        "customerNetworkTier1": false,
                        "planAmount": "",
                        "planAmountFrequency": "",
                        "remainingAmount": "",
                        "metYtdAmount": ""
                    }
                }
            },
            "referralInfo": {
                "referralIndicator": "Y",
                "rLinkEBN": false,
                "cosmosDelegatedEntity": null
            },
            "insuranceInfo": {
                "addressLine1": "UNITEDHEALTHCAREP.O. BOX 31362",
                "addressLine2": "",
                "city": "SALT LAKE CITY",
                "countryCode": "",
                "countrySubDivisionCode": "",
                "found": "true",
                "groupNumber": "55401",
                "insuranceType": "Health Maintenance Organization(HMO) - Medicare Risk",
                "insuranceTypeCode": "HN",
                "lineOfBusiness": "2",
                "paidThroughDate": null,
                "memberId": "970797777",
                "payerName": "UNITEDHEALTHCARE",
                "payerStatus": "Unable to determine",
                "planDescription": "HMOPOS-AARP MEDICARE ADVANTAGE (HMO-POS)",
                "state": "UT",
                "zip": "84131-0362",
                "hraBalance": "",
                "hraMessage": "",
                "hraUnavailableMessage": "",
                "phoneNumber": "",
                "oxfordPlatform": "",
                "payerId": "87726",
                "balancedBillingProtectionActIndicator": false,
                "balancedBillingProtectionActMessage": "",
                "administeredByUhc": false
            },
            "policyInfo": {
                "eligibilityDates": {
                    "startDate": null,
                    "endDate": null
                },
                "memberId": "970797777",
                "planDates": {
                    "startDate": "2020-01-01",
                    "endDate": "2020-12-31"
                },
                "policyStatus": "Active Policy",
                "searchedDates": {
                    "searchStartDate": "2020-09-15",
                    "searchEndDate": ""
                },
                "graceMessageByState": "By law, exchange members who receive a subsidy have a three-month grace period to pay their premiums. We will process claims during the first month. During the second and third month of the grace period, we will pend claims if the premium hasn't been paid. If we receive the premium payment within the grace period, we will process this claim.",
                "gracePaidThrough": null,
                "gracePeriodMonth": null,
                "coverageType": "Medical",
                "nonMedicalPolicyBoolean": false,
                "id": "1",
                "plnBenefit": false
            },
            "primaryCarePhysicianInfo": {
                "pcpFound": "true",
                "lastName": "HARRISON",
                "firstName": "BRUCE",
                "middleName": "",
                "addressLine1": "3444 RIVERLAND DR",
                "addressLine2": "",
                "city": "BRIDGETON",
                "state": "MO",
                "zip": "63044",
                "phoneNumber": "(314) 799-8282",
                "networkStatusCode": "No network status on file",
                "affiliateHospitalName": null,
                "providerGroupName": null
            },
            "transactionId": "wkr6tffgjLqTBycz0oozH0H10QMtfcbDT2iHfThxOIOHH6EKCGqMarBJkmwNT8YnzlR-kRvCLmy8E6SczkCeqg1pmS-vs6jvMpAoN8gOL1stpMmaealShrvJ5gk18P3SsfElT5qcEsCrUZX0IHxeuJCC4Y7OBbpKRuiApMd5VSfoJz1Kz9xoHguFdOf286VAOJH10gm3gONE3eL7ZUDR5DDlobdhf4vWXDgoUg51gJU"
        },
        {
            "patientInfo": [
                {
                    "addressLine1": "1222 VALIANT DRIVE",
                    "addressLine2": "",
                    "city": "FLORIFISSANT",
                    "dateOfBirth": "1945-03-25",
                    "firstName": "ERIC",
                    "gender": "M",
                    "lastName": "GONDORIAN",
                    "middleName": "A",
                    "relationship": "subscriber",
                    "searched": "true",
                    "state": "MO",
                    "zip": "63031",
                    "patientKey": "TrAN2%2FCGn7j7h1mDCCbW7NWvvWNdGEYS75UgKBDX7wFMMfGxWkNHOJGykgnaQi8Zf1FOrtEBIcgb1EnFQ2a%2Fl4IB5PrfqczUPaFgAy4gLqmqB0p%2B9I4vRPDGwGinInO5InphnmzfoTIFbcuO%2BGX5gfTmeliYe1A7mK5RjO0ghHZ2sTy6EXI7lIn61KZxNxZ0%2Fm6AXL1FI6impouYSuTxuC%2F8HjDNaM8p%2Fm9yQsxDg%2F6XyDXV4iAXWDPTB5O1WJJNbmMCvf47Kts4UsjE99EmO3j%2FqA3ez3fV2Z0BL1zHkkH5D5MykSxU7rk9Ipz8LXgenfA0UnJPtUehWAI8ZCjkbp1JZc32KMC4QQBQPjC2iM6lWtLQQ2Bc4hNibpEsCsrea5aZhbbdXdMFz%2BqzSc8cxduBZ%2Beak4NavOKhLCyn5HJKqfruRQbpskLBX1njo%2B2QNv%2BY3%2BaOUe5EAqDsOyXuE4uY8qtbCyG%2BJO9MLHX3quxUUBE0tDoO%2FkRM2ZedaIMl6QfHoFFNeYT2Qa2vC9BRwWkMOhSlb%2Bm4%2BN8uFspa3GxgN7zHznwKkmi3%2B5%2B8Aky589iPlebewYDYGet2LkEWLahqVApqy60tK1MKRGjEI2zhcQ%2F1New2YHeyKN0jTpRWUy67g1KbYcrGUdL2L%2BUcPozoopHSScb46TTCC8J6MQ0xep%2FNbG6oG%2BG9AEpZ%2BVHXzupOlqIr%2BdXBC2cxfXvvM47Bx8Vok8I6CT9i1aFCpLlTPlsaPCi5dzQSK5wTFw5TAJokl4l1g7eSJXwgX6tvhxwADI7QNQJ3IRRoAUD5nMOQAWAZ%2FAkHZzJ%2FOrWmv2Zi5koZSKeJVAAncdRPvhTB%2F1vebOuNqg3R6f66kqdA%2By2L0eVGuQI8eLd4XFphypouOiU%3D",
                    "subscriberBoolean": true
                }
            ],
            "additionalCoverageInfo": [
                {
                    "additionalCoverage": "None",
                    "payerName": "",
                    "memberId": "",
                    "phone": "",
                    "url": "",
                    "insuranceType": "",
                    "payerStatus": "",
                    "coverageType": ""
                }
            ],
            "deductibleInfo": {
                "found": false,
                "nonMainPlan": false,
                "inAndOutOfNetworkOnly": true,
                "message": "Member's plan does not have a deductible",
                "individual": {
                    "found": false,
                    "inNetwork": {
                        "found": false,
                        "customerNetworkTier1": false,
                        "planAmount": "",
                        "planAmountFrequency": "",
                        "remainingAmount": "",
                        "metYtdAmount": ""
                    },
                    "outOfNetwork": {
                        "found": false,
                        "customerNetworkTier1": false,
                        "planAmount": "",
                        "planAmountFrequency": "",
                        "remainingAmount": "",
                        "metYtdAmount": ""
                    },
                    "inNetworkTier1": {
                        "found": false,
                        "customerNetworkTier1": false,
                        "planAmount": "",
                        "planAmountFrequency": "",
                        "remainingAmount": "",
                        "metYtdAmount": ""
                    }
                },
                "family": {
                    "found": false,
                    "inNetwork": {
                        "found": false,
                        "customerNetworkTier1": false,
                        "planAmount": "",
                        "planAmountFrequency": "",
                        "remainingAmount": "",
                        "metYtdAmount": ""
                    },
                    "outOfNetwork": {
                        "found": false,
                        "customerNetworkTier1": false,
                        "planAmount": "",
                        "planAmountFrequency": "",
                        "remainingAmount": "",
                        "metYtdAmount": ""
                    },
                    "inNetworkTier1": {
                        "found": false,
                        "customerNetworkTier1": false,
                        "planAmount": "",
                        "planAmountFrequency": "",
                        "remainingAmount": "",
                        "metYtdAmount": ""
                    }
                }
            },
            "outOfPocketInfo": {
                "found": true,
                "nonMainPlan": false,
                "inAndOutOfNetworkOnly": false,
                "message": "",
                "individual": {
                    "found": true,
                    "inNetwork": {
                        "found": true,
                        "customerNetworkTier1": false,
                        "planAmount": "2900.0",
                        "planAmountFrequency": " (Service Year)",
                        "remainingAmount": "1870.36",
                        "metYtdAmount": "1029.64"
                    },
                    "outOfNetwork": {
                        "found": false,
                        "customerNetworkTier1": false,
                        "planAmount": "",
                        "planAmountFrequency": "",
                        "remainingAmount": "",
                        "metYtdAmount": ""
                    },
                    "inNetworkTier1": {
                        "found": false,
                        "customerNetworkTier1": false,
                        "planAmount": "",
                        "planAmountFrequency": "",
                        "remainingAmount": "",
                        "metYtdAmount": ""
                    }
                },
                "family": {
                    "found": true,
                    "inNetwork": {
                        "found": true,
                        "customerNetworkTier1": false,
                        "planAmount": "99999.99",
                        "planAmountFrequency": " (Service Year)",
                        "remainingAmount": "98970.35",
                        "metYtdAmount": "1029.64"
                    },
                    "outOfNetwork": {
                        "found": false,
                        "customerNetworkTier1": false,
                        "planAmount": "",
                        "planAmountFrequency": "",
                        "remainingAmount": "",
                        "metYtdAmount": ""
                    },
                    "inNetworkTier1": {
                        "found": false,
                        "customerNetworkTier1": false,
                        "planAmount": "",
                        "planAmountFrequency": "",
                        "remainingAmount": "",
                        "metYtdAmount": ""
                    }
                }
            },
            "copayMaxInfo": {
                "found": false,
                "nonMainPlan": false,
                "inAndOutOfNetworkOnly": false,
                "message": "Member's plan does not have a copay maximum",
                "individual": {
                    "found": false,
                    "inNetwork": {
                        "found": false,
                        "customerNetworkTier1": false,
                        "planAmount": "",
                        "planAmountFrequency": "",
                        "remainingAmount": "",
                        "metYtdAmount": ""
                    },
                    "outOfNetwork": {
                        "found": false,
                        "customerNetworkTier1": false,
                        "planAmount": "",
                        "planAmountFrequency": "",
                        "remainingAmount": "",
                        "metYtdAmount": ""
                    },
                    "inNetworkTier1": {
                        "found": false,
                        "customerNetworkTier1": false,
                        "planAmount": "",
                        "planAmountFrequency": "",
                        "remainingAmount": "",
                        "metYtdAmount": ""
                    }
                },
                "family": {
                    "found": false,
                    "inNetwork": {
                        "found": false,
                        "customerNetworkTier1": false,
                        "planAmount": "",
                        "planAmountFrequency": "",
                        "remainingAmount": "",
                        "metYtdAmount": ""
                    },
                    "outOfNetwork": {
                        "found": false,
                        "customerNetworkTier1": false,
                        "planAmount": "",
                        "planAmountFrequency": "",
                        "remainingAmount": "",
                        "metYtdAmount": ""
                    },
                    "inNetworkTier1": {
                        "found": false,
                        "customerNetworkTier1": false,
                        "planAmount": "",
                        "planAmountFrequency": "",
                        "remainingAmount": "",
                        "metYtdAmount": ""
                    }
                }
            },
            "outOfPocketMaxInfo": {
                "found": false,
                "nonMainPlan": false,
                "inAndOutOfNetworkOnly": false,
                "message": "Member's plan does not have an out of pocket 2 maximum",
                "individual": {
                    "found": false,
                    "inNetwork": {
                        "found": false,
                        "customerNetworkTier1": false,
                        "planAmount": "",
                        "planAmountFrequency": "",
                        "remainingAmount": "",
                        "metYtdAmount": ""
                    },
                    "outOfNetwork": {
                        "found": false,
                        "customerNetworkTier1": false,
                        "planAmount": "",
                        "planAmountFrequency": "",
                        "remainingAmount": "",
                        "metYtdAmount": ""
                    },
                    "inNetworkTier1": {
                        "found": false,
                        "customerNetworkTier1": false,
                        "planAmount": "",
                        "planAmountFrequency": "",
                        "remainingAmount": "",
                        "metYtdAmount": ""
                    }
                },
                "family": {
                    "found": false,
                    "inNetwork": {
                        "found": false,
                        "customerNetworkTier1": false,
                        "planAmount": "",
                        "planAmountFrequency": "",
                        "remainingAmount": "",
                        "metYtdAmount": ""
                    },
                    "outOfNetwork": {
                        "found": false,
                        "customerNetworkTier1": false,
                        "planAmount": "",
                        "planAmountFrequency": "",
                        "remainingAmount": "",
                        "metYtdAmount": ""
                    },
                    "inNetworkTier1": {
                        "found": false,
                        "customerNetworkTier1": false,
                        "planAmount": "",
                        "planAmountFrequency": "",
                        "remainingAmount": "",
                        "metYtdAmount": ""
                    }
                }
            },
            "referralInfo": {
                "referralIndicator": "Y",
                "rLinkEBN": false,
                "cosmosDelegatedEntity": null
            },
            "insuranceInfo": {
                "addressLine1": "UNITEDHEALTHCAREP.O. BOX 31362",
                "addressLine2": "",
                "city": "SALT LAKE CITY",
                "countryCode": "",
                "countrySubDivisionCode": "",
                "found": "true",
                "groupNumber": "55402",
                "insuranceType": "Health Maintenance Organization(HMO) - Medicare Risk",
                "insuranceTypeCode": "HN",
                "lineOfBusiness": "2",
                "paidThroughDate": null,
                "memberId": "970797777",
                "payerName": "UNITEDHEALTHCARE",
                "payerStatus": "Unable to determine",
                "planDescription": "HMOPOS-AARP MEDICARE ADVANTAGE (HMO-POS)",
                "state": "UT",
                "zip": "84131-0362",
                "hraBalance": "",
                "hraMessage": "",
                "hraUnavailableMessage": "",
                "phoneNumber": "",
                "oxfordPlatform": "",
                "payerId": "87726",
                "balancedBillingProtectionActIndicator": false,
                "balancedBillingProtectionActMessage": "",
                "administeredByUhc": false
            },
            "policyInfo": {
                "eligibilityDates": {
                    "startDate": null,
                    "endDate": null
                },
                "memberId": "970797777",
                "planDates": {
                    "startDate": "2020-01-01",
                    "endDate": "2020-12-31"
                },
                "policyStatus": "Active Policy",
                "searchedDates": {
                    "searchStartDate": "2020-09-15",
                    "searchEndDate": ""
                },
                "graceMessageByState": "By law, exchange members who receive a subsidy have a three-month grace period to pay their premiums. We will process claims during the first month. During the second and third month of the grace period, we will pend claims if the premium hasn't been paid. If we receive the premium payment within the grace period, we will process this claim.",
                "gracePaidThrough": null,
                "gracePeriodMonth": null,
                "coverageType": "Medical",
                "nonMedicalPolicyBoolean": false,
                "id": "1",
                "plnBenefit": false
            },
            "primaryCarePhysicianInfo": {
                "pcpFound": "true",
                "lastName": "HARRISON",
                "firstName": "BRUCE",
                "middleName": "",
                "addressLine1": "3444 RIVERLAND DR",
                "addressLine2": "",
                "city": "BRIDGETON",
                "state": "MO",
                "zip": "63044",
                "phoneNumber": "(314) 799-8282",
                "networkStatusCode": "No network status on file",
                "affiliateHospitalName": null,
                "providerGroupName": null
            },
            "transactionId": "qvl7DsfgjLqTBycz0oozH0H10QMtfcbDT2iHfThxOIOHH6EKCGqMarBJkmwNT8YnzlR-kRvCLmy8E6SczkCeqg1pmS-vs6jvMpAoN8gOL1stpMmaealShrvJ5gk18P3SsfElT5qcEsCrUZX0IHxeuJCC4Y7OBbpKRuiApMd5VSfoJz1Kz9xoHguFdOf286VAOJH10gm3gONE3eL7ZUDR5DDlobdhf4vWXDgoUg51gJU"
        }
    ],
    "requestingProvider": {
        "providerFirstName": "MARK",
        "providerMiddleName": null,
        "providerLastName": "Our Lady of the Lake Reg Med Ctr",
        "providerNameID": null,
        "taxIdNumber": null,
        "corporateTaxOwnerID": null,
        "corporateTaxOwnerName": null,
        "organizationName": null,
        "organizationID": null,
        "facilityName": null,
        "npi": "720423222"
    },
    "requestingProviderAddresses": [],
    "searchQuery": {
        "memberId": "970797777",
        "lastName": "0",
        "firstName": "0",
        "dateOfBirth": "19450325",
        "payerID": "87726",
        "payerName": "0",
        "serviceStart": "0",
        "serviceEnd": "0",
        "middleName": "0",
        "gender": "0",
        "ssn": "0",
        "city": "0",
        "state": "0",
        "zip": "0",
        "groupNumber": "0",
        "serviceTypeCode": "0",
        "providerLastName": "Our Lady of the Lake Reg Med Ctr",
        "providerFirstName": "MARK",
        "providerNameID": "0",
        "corporateTaxOwnerID": "0",
        "corporateTaxOwnerName": "0",
        "organizationName": "0",
        "organizationID": "0",
        "taxIdNumber": "0",
        "searchOption": "MemberIDDateOfBirth",
        "payerLabel": "0",
        "npi": "720423222"
    }
}
