{
    "moreRecordsLeft": false,
    "startRow": 0,
    "totalRecords": 2,
    "scrollId": null,
    "recordsList": [
        {
            "objectId": "ab7aa4f5-c1fc-4fd3-8022-e4f0ab0458d7|u_mli_elgs_2019-08_v3",
            "objectName": null,
            "mimeType": null,
            "contentType": "PDF",
            "contentSize": 4074,
            "contentFileExtension": null,
            "totalPages": 6,
            "contentStream": null,
            "attributes": [
                {
                    "classId": 0,
                    "id": 0,
                    "alias1": null,
                    "alias2": null,
                    "conversionFormat": null,
                    "federateSearchAlias": null,
                    "labelName": "u_ltr_gen_req_id",
                    "wildCardIndicator": null,
                    "wildCardMinLengthRequired": null,
                    "legacyLabelName": "u_ltr_gen_req_id",
                    "physicalName": "u_ltr_gen_req_id",
                    "priority": null,
                    "sortNumericInd": null,
                    "value": "179309624253882202"
                },
                {
                    "classId": 0,
                    "id": 0,
                    "alias1": null,
                    "alias2": null,
                    "conversionFormat": null,
                    "federateSearchAlias": null,
                    "labelName": "u_subject",
                    "wildCardIndicator": null,
                    "wildCardMinLengthRequired": null,
                    "legacyLabelName": "u_subject",
                    "physicalName": "u_subject",
                    "priority": null,
                    "sortNumericInd": null,
                    "value": "CLAIM INFORMATION REQUEST"
                },
                {
                    "classId": 0,
                    "id": 0,
                    "alias1": null,
                    "alias2": null,
                    "conversionFormat": null,
                    "federateSearchAlias": null,
                    "labelName": "r_content_size",
                    "wildCardIndicator": null,
                    "wildCardMinLengthRequired": null,
                    "legacyLabelName": "r_content_size",
                    "physicalName": "r_content_size",
                    "priority": null,
                    "sortNumericInd": null,
                    "value": "4074"
                },
                {
                    "classId": 0,
                    "id": 0,
                    "alias1": null,
                    "alias2": null,
                    "conversionFormat": null,
                    "federateSearchAlias": null,
                    "labelName": "u_physician_provider_nm",
                    "wildCardIndicator": null,
                    "wildCardMinLengthRequired": null,
                    "legacyLabelName": "u_physician_provider_nm",
                    "physicalName": "u_physician_provider_nm",
                    "priority": null,
                    "sortNumericInd": null,
                    "value": "TEXAS HLTH HARRIS METH HOSP"
                },
                {
                    "classId": 0,
                    "id": 0,
                    "alias1": null,
                    "alias2": null,
                    "conversionFormat": null,
                    "federateSearchAlias": null,
                    "labelName": "a_content_type",
                    "wildCardIndicator": null,
                    "wildCardMinLengthRequired": null,
                    "legacyLabelName": "a_content_type",
                    "physicalName": "a_content_type",
                    "priority": null,
                    "sortNumericInd": null,
                    "value": "PDF"
                },
                {
                    "classId": 0,
                    "id": 0,
                    "alias1": null,
                    "alias2": null,
                    "conversionFormat": null,
                    "federateSearchAlias": null,
                    "labelName": "u_physician_provider_tax_id",
                    "wildCardIndicator": null,
                    "wildCardMinLengthRequired": null,
                    "legacyLabelName": "u_physician_provider_tax_id",
                    "physicalName": "u_physician_provider_tax_id",
                    "priority": null,
                    "sortNumericInd": null,
                    "value": "741777515"
                },
                {
                    "classId": 0,
                    "id": 0,
                    "alias1": null,
                    "alias2": null,
                    "conversionFormat": null,
                    "federateSearchAlias": null,
                    "labelName": "u_icn_nbr",
                    "wildCardIndicator": null,
                    "wildCardMinLengthRequired": null,
                    "legacyLabelName": "u_icn_nbr",
                    "physicalName": "u_icn_nbr",
                    "priority": null,
                    "sortNumericInd": null,
                    "value": "7840302400"
                },
                {
                    "classId": 0,
                    "id": 0,
                    "alias1": null,
                    "alias2": null,
                    "conversionFormat": null,
                    "federateSearchAlias": null,
                    "labelName": "group_names",
                    "wildCardIndicator": null,
                    "wildCardMinLengthRequired": null,
                    "legacyLabelName": "group_names",
                    "physicalName": "group_names",
                    "priority": null,
                    "sortNumericInd": null,
                    "value": "[\"edmfm_prd_mli_elgs_ro\",\"edmfm_prd_mli_elgs_uhc_ro\"]"
                },
                {
                    "classId": 0,
                    "id": 0,
                    "alias1": null,
                    "alias2": null,
                    "conversionFormat": null,
                    "federateSearchAlias": null,
                    "labelName": "u_patient_fn_ln",
                    "wildCardIndicator": null,
                    "wildCardMinLengthRequired": null,
                    "legacyLabelName": "u_patient_fn_ln",
                    "physicalName": "u_patient_fn_ln",
                    "priority": null,
                    "sortNumericInd": null,
                    "value": "DAVE BURROWS"
                },
                {
                    "classId": 0,
                    "id": 0,
                    "alias1": null,
                    "alias2": null,
                    "conversionFormat": null,
                    "federateSearchAlias": null,
                    "labelName": "u_recip_data_mail_cd",
                    "wildCardIndicator": null,
                    "wildCardMinLengthRequired": null,
                    "legacyLabelName": "u_recip_data_mail_cd",
                    "physicalName": "u_recip_data_mail_cd",
                    "priority": null,
                    "sortNumericInd": null,
                    "value": "CA"
                },
                {
                    "classId": 0,
                    "id": 0,
                    "alias1": null,
                    "alias2": null,
                    "conversionFormat": null,
                    "federateSearchAlias": null,
                    "labelName": "urlpath",
                    "wildCardIndicator": null,
                    "wildCardMinLengthRequired": null,
                    "legacyLabelName": "urlpath",
                    "physicalName": "urlpath",
                    "priority": null,
                    "sortNumericInd": null,
                    "value": "https://doc360-riofs-4.optum.com/data3/u_mli_elgs/2019-08-24/6052154/ab7aa4f5-c1fc-4fd3-8022-e4f0ab0458d7.pdf.zip"
                },
                {
                    "classId": 0,
                    "id": 0,
                    "alias1": null,
                    "alias2": null,
                    "conversionFormat": null,
                    "federateSearchAlias": null,
                    "labelName": "u_letter_type",
                    "wildCardIndicator": null,
                    "wildCardMinLengthRequired": null,
                    "legacyLabelName": "u_letter_type",
                    "physicalName": "u_letter_type",
                    "priority": null,
                    "sortNumericInd": null,
                    "value": "C8"
                },
                {
                    "classId": 0,
                    "id": 0,
                    "alias1": null,
                    "alias2": null,
                    "conversionFormat": null,
                    "federateSearchAlias": null,
                    "labelName": "u_policy_nbr",
                    "wildCardIndicator": null,
                    "wildCardMinLengthRequired": null,
                    "legacyLabelName": "u_policy_nbr",
                    "physicalName": "u_policy_nbr",
                    "priority": null,
                    "sortNumericInd": null,
                    "value": "706288"
                },
                {
                    "classId": 0,
                    "id": 0,
                    "alias1": null,
                    "alias2": null,
                    "conversionFormat": null,
                    "federateSearchAlias": null,
                    "labelName": "u_emp_fn_ln",
                    "wildCardIndicator": null,
                    "wildCardMinLengthRequired": null,
                    "legacyLabelName": "u_emp_fn_ln",
                    "physicalName": "u_emp_fn_ln",
                    "priority": null,
                    "sortNumericInd": null,
                    "value": "ALEX GRANT"
                },
                {
                    "classId": 0,
                    "id": 0,
                    "alias1": null,
                    "alias2": null,
                    "conversionFormat": null,
                    "federateSearchAlias": null,
                    "labelName": "u_gbl_doc_id",
                    "wildCardIndicator": null,
                    "wildCardMinLengthRequired": null,
                    "legacyLabelName": "u_gbl_doc_id",
                    "physicalName": "u_gbl_doc_id",
                    "priority": null,
                    "sortNumericInd": null,
                    "value": "ab7aa4f5-c1fc-4fd3-8022-e4f0ab0458d7|u_mli_elgs_2019-08_v3"
                },
                {
                    "classId": 0,
                    "id": 0,
                    "alias1": null,
                    "alias2": null,
                    "conversionFormat": null,
                    "federateSearchAlias": null,
                    "labelName": "object_name",
                    "wildCardIndicator": null,
                    "wildCardMinLengthRequired": null,
                    "legacyLabelName": "object_name",
                    "physicalName": "object_name",
                    "priority": null,
                    "sortNumericInd": null,
                    "value": "ab7aa4f5-c1fc-4fd3-8022-e4f0ab0458d7.pdf.zip"
                },
                {
                    "classId": 0,
                    "id": 0,
                    "alias1": null,
                    "alias2": null,
                    "conversionFormat": null,
                    "federateSearchAlias": null,
                    "labelName": "u_legal_hold",
                    "wildCardIndicator": null,
                    "wildCardMinLengthRequired": null,
                    "legacyLabelName": "u_legal_hold",
                    "physicalName": "u_legal_hold",
                    "priority": null,
                    "sortNumericInd": null,
                    "value": "false"
                },
                {
                    "classId": 0,
                    "id": 0,
                    "alias1": null,
                    "alias2": null,
                    "conversionFormat": null,
                    "federateSearchAlias": null,
                    "labelName": "u_emp_id",
                    "wildCardIndicator": null,
                    "wildCardMinLengthRequired": null,
                    "legacyLabelName": "u_emp_id",
                    "physicalName": "u_emp_id",
                    "priority": null,
                    "sortNumericInd": null,
                    "value": "929394959"
                },
                {
                    "classId": 0,
                    "id": 0,
                    "alias1": null,
                    "alias2": null,
                    "conversionFormat": null,
                    "federateSearchAlias": null,
                    "labelName": "u_orig_creation_date",
                    "wildCardIndicator": null,
                    "wildCardMinLengthRequired": null,
                    "legacyLabelName": "u_orig_creation_date",
                    "physicalName": "u_orig_creation_date",
                    "priority": null,
                    "sortNumericInd": null,
                    "value": "2019-08-24T00:00:00.000Z"
                },
                {
                    "classId": 0,
                    "id": 0,
                    "alias1": null,
                    "alias2": null,
                    "conversionFormat": null,
                    "federateSearchAlias": null,
                    "labelName": "r_page_cnt",
                    "wildCardIndicator": null,
                    "wildCardMinLengthRequired": null,
                    "legacyLabelName": "r_page_cnt",
                    "physicalName": "r_page_cnt",
                    "priority": null,
                    "sortNumericInd": null,
                    "value": "6"
                },
                {
                    "classId": 0,
                    "id": 0,
                    "alias1": null,
                    "alias2": null,
                    "conversionFormat": null,
                    "federateSearchAlias": null,
                    "labelName": "u_process_ltr_dt",
                    "wildCardIndicator": null,
                    "wildCardMinLengthRequired": null,
                    "legacyLabelName": "u_process_ltr_dt",
                    "physicalName": "u_process_ltr_dt",
                    "priority": null,
                    "sortNumericInd": null,
                    "value": "2019-05-23T00:00:00.000Z"
                },
                {
                    "classId": 0,
                    "id": 0,
                    "alias1": null,
                    "alias2": null,
                    "conversionFormat": null,
                    "federateSearchAlias": null,
                    "labelName": "r_object_id",
                    "wildCardIndicator": null,
                    "wildCardMinLengthRequired": null,
                    "legacyLabelName": "r_object_id",
                    "physicalName": "r_object_id",
                    "priority": null,
                    "sortNumericInd": null,
                    "value": "ab7aa4f5-c1fc-4fd3-8022-e4f0ab0458d7|u_mli_elgs_2019-08_v3"
                },
                {
                    "classId": 0,
                    "id": 0,
                    "alias1": null,
                    "alias2": null,
                    "conversionFormat": null,
                    "federateSearchAlias": null,
                    "labelName": "u_reset",
                    "wildCardIndicator": null,
                    "wildCardMinLengthRequired": null,
                    "legacyLabelName": "u_reset",
                    "physicalName": "u_reset",
                    "priority": null,
                    "sortNumericInd": null,
                    "value": ""
                },
                {
                    "classId": 0,
                    "id": 0,
                    "alias1": null,
                    "alias2": null,
                    "conversionFormat": null,
                    "federateSearchAlias": null,
                    "labelName": "u_compound_seq",
                    "wildCardIndicator": null,
                    "wildCardMinLengthRequired": null,
                    "legacyLabelName": "u_compound_seq",
                    "physicalName": "u_compound_seq",
                    "priority": null,
                    "sortNumericInd": null,
                    "value": ""
                },
                {
                    "classId": 0,
                    "id": 0,
                    "alias1": null,
                    "alias2": null,
                    "conversionFormat": null,
                    "federateSearchAlias": null,
                    "labelName": "r_full_content_size",
                    "wildCardIndicator": null,
                    "wildCardMinLengthRequired": null,
                    "legacyLabelName": "r_full_content_size",
                    "physicalName": "r_full_content_size",
                    "priority": null,
                    "sortNumericInd": null,
                    "value": ""
                },
                {
                    "classId": 0,
                    "id": 0,
                    "alias1": null,
                    "alias2": null,
                    "conversionFormat": null,
                    "federateSearchAlias": null,
                    "labelName": "u_checkbox",
                    "wildCardIndicator": null,
                    "wildCardMinLengthRequired": null,
                    "legacyLabelName": "u_checkbox",
                    "physicalName": "u_checkbox",
                    "priority": null,
                    "sortNumericInd": null,
                    "value": ""
                },
                {
                    "classId": 0,
                    "id": 0,
                    "alias1": null,
                    "alias2": null,
                    "conversionFormat": null,
                    "federateSearchAlias": null,
                    "labelName": "u_search",
                    "wildCardIndicator": null,
                    "wildCardMinLengthRequired": null,
                    "legacyLabelName": "u_search",
                    "physicalName": "u_search",
                    "priority": null,
                    "sortNumericInd": null,
                    "value": ""
                },
                {
                    "classId": 0,
                    "id": 0,
                    "alias1": null,
                    "alias2": null,
                    "conversionFormat": null,
                    "federateSearchAlias": null,
                    "labelName": "u_compound_doc",
                    "wildCardIndicator": null,
                    "wildCardMinLengthRequired": null,
                    "legacyLabelName": "u_compound_doc",
                    "physicalName": "u_compound_doc",
                    "priority": null,
                    "sortNumericInd": null,
                    "value": ""
                },
                {
                    "classId": 0,
                    "id": 0,
                    "alias1": null,
                    "alias2": null,
                    "conversionFormat": null,
                    "federateSearchAlias": null,
                    "labelName": "r_creation_date",
                    "wildCardIndicator": null,
                    "wildCardMinLengthRequired": null,
                    "legacyLabelName": "r_creation_date",
                    "physicalName": "r_creation_date",
                    "priority": null,
                    "sortNumericInd": null,
                    "value": ""
                },
                {
                    "classId": 0,
                    "id": 0,
                    "alias1": null,
                    "alias2": null,
                    "conversionFormat": null,
                    "federateSearchAlias": null,
                    "labelName": "u_legal_case_id",
                    "wildCardIndicator": null,
                    "wildCardMinLengthRequired": null,
                    "legacyLabelName": "u_legal_case_id",
                    "physicalName": "u_legal_case_id",
                    "priority": null,
                    "sortNumericInd": null,
                    "value": ""
                }
            ]
        },
        {
            "objectId": "2efa117f-4115-4bee-a7d5-1d913719fdb1|u_mli_elgs_2019-08_v3",
            "objectName": null,
            "mimeType": null,
            "contentType": "PDF",
            "contentSize": 4005,
            "contentFileExtension": null,
            "totalPages": 4,
            "contentStream": null,
            "attributes": [
                {
                    "classId": 0,
                    "id": 0,
                    "alias1": null,
                    "alias2": null,
                    "conversionFormat": null,
                    "federateSearchAlias": null,
                    "labelName": "u_ltr_gen_req_id",
                    "wildCardIndicator": null,
                    "wildCardMinLengthRequired": null,
                    "legacyLabelName": "u_ltr_gen_req_id",
                    "physicalName": "u_ltr_gen_req_id",
                    "priority": null,
                    "sortNumericInd": null,
                    "value": "179309624253882196"
                },
                {
                    "classId": 0,
                    "id": 0,
                    "alias1": null,
                    "alias2": null,
                    "conversionFormat": null,
                    "federateSearchAlias": null,
                    "labelName": "u_subject",
                    "wildCardIndicator": null,
                    "wildCardMinLengthRequired": null,
                    "legacyLabelName": "u_subject",
                    "physicalName": "u_subject",
                    "priority": null,
                    "sortNumericInd": null,
                    "value": "CLAIM INFORMATION REQUEST"
                },
                {
                    "classId": 0,
                    "id": 0,
                    "alias1": null,
                    "alias2": null,
                    "conversionFormat": null,
                    "federateSearchAlias": null,
                    "labelName": "r_content_size",
                    "wildCardIndicator": null,
                    "wildCardMinLengthRequired": null,
                    "legacyLabelName": "r_content_size",
                    "physicalName": "r_content_size",
                    "priority": null,
                    "sortNumericInd": null,
                    "value": "4005"
                },
                {
                    "classId": 0,
                    "id": 0,
                    "alias1": null,
                    "alias2": null,
                    "conversionFormat": null,
                    "federateSearchAlias": null,
                    "labelName": "u_physician_provider_nm",
                    "wildCardIndicator": null,
                    "wildCardMinLengthRequired": null,
                    "legacyLabelName": "u_physician_provider_nm",
                    "physicalName": "u_physician_provider_nm",
                    "priority": null,
                    "sortNumericInd": null,
                    "value": "TEXAS HLTH HARRIS METH HOSP"
                },
                {
                    "classId": 0,
                    "id": 0,
                    "alias1": null,
                    "alias2": null,
                    "conversionFormat": null,
                    "federateSearchAlias": null,
                    "labelName": "a_content_type",
                    "wildCardIndicator": null,
                    "wildCardMinLengthRequired": null,
                    "legacyLabelName": "a_content_type",
                    "physicalName": "a_content_type",
                    "priority": null,
                    "sortNumericInd": null,
                    "value": "PDF"
                },
                {
                    "classId": 0,
                    "id": 0,
                    "alias1": null,
                    "alias2": null,
                    "conversionFormat": null,
                    "federateSearchAlias": null,
                    "labelName": "u_physician_provider_tax_id",
                    "wildCardIndicator": null,
                    "wildCardMinLengthRequired": null,
                    "legacyLabelName": "u_physician_provider_tax_id",
                    "physicalName": "u_physician_provider_tax_id",
                    "priority": null,
                    "sortNumericInd": null,
                    "value": "741777515"
                },
                {
                    "classId": 0,
                    "id": 0,
                    "alias1": null,
                    "alias2": null,
                    "conversionFormat": null,
                    "federateSearchAlias": null,
                    "labelName": "u_icn_nbr",
                    "wildCardIndicator": null,
                    "wildCardMinLengthRequired": null,
                    "legacyLabelName": "u_icn_nbr",
                    "physicalName": "u_icn_nbr",
                    "priority": null,
                    "sortNumericInd": null,
                    "value": "7840302400"
                },
                {
                    "classId": 0,
                    "id": 0,
                    "alias1": null,
                    "alias2": null,
                    "conversionFormat": null,
                    "federateSearchAlias": null,
                    "labelName": "group_names",
                    "wildCardIndicator": null,
                    "wildCardMinLengthRequired": null,
                    "legacyLabelName": "group_names",
                    "physicalName": "group_names",
                    "priority": null,
                    "sortNumericInd": null,
                    "value": "[\"edmfm_prd_mli_elgs_ro\",\"edmfm_prd_mli_elgs_uhc_ro\"]"
                },
                {
                    "classId": 0,
                    "id": 0,
                    "alias1": null,
                    "alias2": null,
                    "conversionFormat": null,
                    "federateSearchAlias": null,
                    "labelName": "u_patient_fn_ln",
                    "wildCardIndicator": null,
                    "wildCardMinLengthRequired": null,
                    "legacyLabelName": "u_patient_fn_ln",
                    "physicalName": "u_patient_fn_ln",
                    "priority": null,
                    "sortNumericInd": null,
                    "value": "DAVE BURROWS"
                },
                {
                    "classId": 0,
                    "id": 0,
                    "alias1": null,
                    "alias2": null,
                    "conversionFormat": null,
                    "federateSearchAlias": null,
                    "labelName": "u_recip_data_mail_cd",
                    "wildCardIndicator": null,
                    "wildCardMinLengthRequired": null,
                    "legacyLabelName": "u_recip_data_mail_cd",
                    "physicalName": "u_recip_data_mail_cd",
                    "priority": null,
                    "sortNumericInd": null,
                    "value": "SA"
                },
                {
                    "classId": 0,
                    "id": 0,
                    "alias1": null,
                    "alias2": null,
                    "conversionFormat": null,
                    "federateSearchAlias": null,
                    "labelName": "urlpath",
                    "wildCardIndicator": null,
                    "wildCardMinLengthRequired": null,
                    "legacyLabelName": "urlpath",
                    "physicalName": "urlpath",
                    "priority": null,
                    "sortNumericInd": null,
                    "value": "https://doc360-riofs-4.optum.com/data3/u_mli_elgs/2019-08-24/6052154/2efa117f-4115-4bee-a7d5-1d913719fdb1.pdf.zip"
                },
                {
                    "classId": 0,
                    "id": 0,
                    "alias1": null,
                    "alias2": null,
                    "conversionFormat": null,
                    "federateSearchAlias": null,
                    "labelName": "u_letter_type",
                    "wildCardIndicator": null,
                    "wildCardMinLengthRequired": null,
                    "legacyLabelName": "u_letter_type",
                    "physicalName": "u_letter_type",
                    "priority": null,
                    "sortNumericInd": null,
                    "value": "C1"
                },
                {
                    "classId": 0,
                    "id": 0,
                    "alias1": null,
                    "alias2": null,
                    "conversionFormat": null,
                    "federateSearchAlias": null,
                    "labelName": "u_policy_nbr",
                    "wildCardIndicator": null,
                    "wildCardMinLengthRequired": null,
                    "legacyLabelName": "u_policy_nbr",
                    "physicalName": "u_policy_nbr",
                    "priority": null,
                    "sortNumericInd": null,
                    "value": "706288"
                },
                {
                    "classId": 0,
                    "id": 0,
                    "alias1": null,
                    "alias2": null,
                    "conversionFormat": null,
                    "federateSearchAlias": null,
                    "labelName": "u_emp_fn_ln",
                    "wildCardIndicator": null,
                    "wildCardMinLengthRequired": null,
                    "legacyLabelName": "u_emp_fn_ln",
                    "physicalName": "u_emp_fn_ln",
                    "priority": null,
                    "sortNumericInd": null,
                    "value": "ALEX GRANT"
                },
                {
                    "classId": 0,
                    "id": 0,
                    "alias1": null,
                    "alias2": null,
                    "conversionFormat": null,
                    "federateSearchAlias": null,
                    "labelName": "u_gbl_doc_id",
                    "wildCardIndicator": null,
                    "wildCardMinLengthRequired": null,
                    "legacyLabelName": "u_gbl_doc_id",
                    "physicalName": "u_gbl_doc_id",
                    "priority": null,
                    "sortNumericInd": null,
                    "value": "2efa117f-4115-4bee-a7d5-1d913719fdb1|u_mli_elgs_2019-08_v3"
                },
                {
                    "classId": 0,
                    "id": 0,
                    "alias1": null,
                    "alias2": null,
                    "conversionFormat": null,
                    "federateSearchAlias": null,
                    "labelName": "object_name",
                    "wildCardIndicator": null,
                    "wildCardMinLengthRequired": null,
                    "legacyLabelName": "object_name",
                    "physicalName": "object_name",
                    "priority": null,
                    "sortNumericInd": null,
                    "value": "2efa117f-4115-4bee-a7d5-1d913719fdb1.pdf.zip"
                },
                {
                    "classId": 0,
                    "id": 0,
                    "alias1": null,
                    "alias2": null,
                    "conversionFormat": null,
                    "federateSearchAlias": null,
                    "labelName": "u_legal_hold",
                    "wildCardIndicator": null,
                    "wildCardMinLengthRequired": null,
                    "legacyLabelName": "u_legal_hold",
                    "physicalName": "u_legal_hold",
                    "priority": null,
                    "sortNumericInd": null,
                    "value": "false"
                },
                {
                    "classId": 0,
                    "id": 0,
                    "alias1": null,
                    "alias2": null,
                    "conversionFormat": null,
                    "federateSearchAlias": null,
                    "labelName": "u_emp_id",
                    "wildCardIndicator": null,
                    "wildCardMinLengthRequired": null,
                    "legacyLabelName": "u_emp_id",
                    "physicalName": "u_emp_id",
                    "priority": null,
                    "sortNumericInd": null,
                    "value": "929394959"
                },
                {
                    "classId": 0,
                    "id": 0,
                    "alias1": null,
                    "alias2": null,
                    "conversionFormat": null,
                    "federateSearchAlias": null,
                    "labelName": "u_orig_creation_date",
                    "wildCardIndicator": null,
                    "wildCardMinLengthRequired": null,
                    "legacyLabelName": "u_orig_creation_date",
                    "physicalName": "u_orig_creation_date",
                    "priority": null,
                    "sortNumericInd": null,
                    "value": "2019-08-24T00:00:00.000Z"
                },
                {
                    "classId": 0,
                    "id": 0,
                    "alias1": null,
                    "alias2": null,
                    "conversionFormat": null,
                    "federateSearchAlias": null,
                    "labelName": "r_page_cnt",
                    "wildCardIndicator": null,
                    "wildCardMinLengthRequired": null,
                    "legacyLabelName": "r_page_cnt",
                    "physicalName": "r_page_cnt",
                    "priority": null,
                    "sortNumericInd": null,
                    "value": "4"
                },
                {
                    "classId": 0,
                    "id": 0,
                    "alias1": null,
                    "alias2": null,
                    "conversionFormat": null,
                    "federateSearchAlias": null,
                    "labelName": "u_process_ltr_dt",
                    "wildCardIndicator": null,
                    "wildCardMinLengthRequired": null,
                    "legacyLabelName": "u_process_ltr_dt",
                    "physicalName": "u_process_ltr_dt",
                    "priority": null,
                    "sortNumericInd": null,
                    "value": "2019-05-23T00:00:00.000Z"
                },
                {
                    "classId": 0,
                    "id": 0,
                    "alias1": null,
                    "alias2": null,
                    "conversionFormat": null,
                    "federateSearchAlias": null,
                    "labelName": "r_object_id",
                    "wildCardIndicator": null,
                    "wildCardMinLengthRequired": null,
                    "legacyLabelName": "r_object_id",
                    "physicalName": "r_object_id",
                    "priority": null,
                    "sortNumericInd": null,
                    "value": "2efa117f-4115-4bee-a7d5-1d913719fdb1|u_mli_elgs_2019-08_v3"
                },
                {
                    "classId": 0,
                    "id": 0,
                    "alias1": null,
                    "alias2": null,
                    "conversionFormat": null,
                    "federateSearchAlias": null,
                    "labelName": "u_reset",
                    "wildCardIndicator": null,
                    "wildCardMinLengthRequired": null,
                    "legacyLabelName": "u_reset",
                    "physicalName": "u_reset",
                    "priority": null,
                    "sortNumericInd": null,
                    "value": ""
                },
                {
                    "classId": 0,
                    "id": 0,
                    "alias1": null,
                    "alias2": null,
                    "conversionFormat": null,
                    "federateSearchAlias": null,
                    "labelName": "u_compound_seq",
                    "wildCardIndicator": null,
                    "wildCardMinLengthRequired": null,
                    "legacyLabelName": "u_compound_seq",
                    "physicalName": "u_compound_seq",
                    "priority": null,
                    "sortNumericInd": null,
                    "value": ""
                },
                {
                    "classId": 0,
                    "id": 0,
                    "alias1": null,
                    "alias2": null,
                    "conversionFormat": null,
                    "federateSearchAlias": null,
                    "labelName": "r_full_content_size",
                    "wildCardIndicator": null,
                    "wildCardMinLengthRequired": null,
                    "legacyLabelName": "r_full_content_size",
                    "physicalName": "r_full_content_size",
                    "priority": null,
                    "sortNumericInd": null,
                    "value": ""
                },
                {
                    "classId": 0,
                    "id": 0,
                    "alias1": null,
                    "alias2": null,
                    "conversionFormat": null,
                    "federateSearchAlias": null,
                    "labelName": "u_checkbox",
                    "wildCardIndicator": null,
                    "wildCardMinLengthRequired": null,
                    "legacyLabelName": "u_checkbox",
                    "physicalName": "u_checkbox",
                    "priority": null,
                    "sortNumericInd": null,
                    "value": ""
                },
                {
                    "classId": 0,
                    "id": 0,
                    "alias1": null,
                    "alias2": null,
                    "conversionFormat": null,
                    "federateSearchAlias": null,
                    "labelName": "u_search",
                    "wildCardIndicator": null,
                    "wildCardMinLengthRequired": null,
                    "legacyLabelName": "u_search",
                    "physicalName": "u_search",
                    "priority": null,
                    "sortNumericInd": null,
                    "value": ""
                },
                {
                    "classId": 0,
                    "id": 0,
                    "alias1": null,
                    "alias2": null,
                    "conversionFormat": null,
                    "federateSearchAlias": null,
                    "labelName": "u_compound_doc",
                    "wildCardIndicator": null,
                    "wildCardMinLengthRequired": null,
                    "legacyLabelName": "u_compound_doc",
                    "physicalName": "u_compound_doc",
                    "priority": null,
                    "sortNumericInd": null,
                    "value": ""
                },
                {
                    "classId": 0,
                    "id": 0,
                    "alias1": null,
                    "alias2": null,
                    "conversionFormat": null,
                    "federateSearchAlias": null,
                    "labelName": "r_creation_date",
                    "wildCardIndicator": null,
                    "wildCardMinLengthRequired": null,
                    "legacyLabelName": "r_creation_date",
                    "physicalName": "r_creation_date",
                    "priority": null,
                    "sortNumericInd": null,
                    "value": ""
                },
                {
                    "classId": 0,
                    "id": 0,
                    "alias1": null,
                    "alias2": null,
                    "conversionFormat": null,
                    "federateSearchAlias": null,
                    "labelName": "u_legal_case_id",
                    "wildCardIndicator": null,
                    "wildCardMinLengthRequired": null,
                    "legacyLabelName": "u_legal_case_id",
                    "physicalName": "u_legal_case_id",
                    "priority": null,
                    "sortNumericInd": null,
                    "value": ""
                }
            ]
        }
    ]
}
