{
  "appPageId" : "a814cede-8a96-414c-8774-0d3198c7a68e",
  "componentName" : "siteforce:sldsOneColLayout",
  "id" : "38808252-5a1f-4c05-b8f3-950979218445",
  "label" : "Group Related List",
  "regions" : [ {
    "id" : "1686b662-9912-431b-a1ff-16487cece601",
    "regionName" : "header",
    "type" : "region"
  }, {
    "components" : [ {
      "componentAttributes" : {
        "customTitle" : "",
        "parentRecordId" : "{!recordId}",
        "relatedListName" : "{!relationshipApiName}",
        "showBreadCrumbs" : true,
        "showCustomTitle" : false,
        "showManualRefreshButton" : true,
        "showRowNumbers" : true
      },
      "componentName" : "forceCommunity:relatedList",
      "id" : "2cdfbea5-cb69-4e7c-bdaf-e50da1d977cb",
      "renderPriority" : "NEUTRAL",
      "renditionMap" : { },
      "type" : "component"
    } ],
    "id" : "5707001e-f329-4878-bbb6-8ff6f23f862f",
    "regionName" : "content",
    "type" : "region"
  }, {
    "id" : "de4c54e7-a1bf-48d2-95c0-6bef7c323985",
    "regionName" : "footer",
    "type" : "region"
  } ],
  "themeLayoutType" : "Inner",
  "type" : "view",
  "viewType" : "relatedlist-0F9"
}